{
"meta":{"test_sets":[],"test_metrics":[],"learn_metrics":[{"best_value":"Min","name":"RMSE"}],"launch_mode":"Train","parameters":"","iteration_count":1000,"learn_sets":["learn"],"name":"experiment"},
"iterations":[
{"learn":[14.61268541],"iteration":0,"passed_time":0.1535858903,"remaining_time":153.4323044},
{"learn":[14.23196558],"iteration":1,"passed_time":0.1581910296,"remaining_time":78.93732375},
{"learn":[13.86674177],"iteration":2,"passed_time":0.161816094,"remaining_time":53.77688189},
{"learn":[13.49946468],"iteration":3,"passed_time":0.163644818,"remaining_time":40.74755968},
{"learn":[13.16661202],"iteration":4,"passed_time":0.165910131,"remaining_time":33.01611606},
{"learn":[12.85632158],"iteration":5,"passed_time":0.168248437,"remaining_time":27.87315773},
{"learn":[12.56784336],"iteration":6,"passed_time":0.1701466291,"remaining_time":24.13651467},
{"learn":[12.31617801],"iteration":7,"passed_time":0.1720656297,"remaining_time":21.33613808},
{"learn":[12.01509946],"iteration":8,"passed_time":0.1742086883,"remaining_time":19.18231223},
{"learn":[11.71512571],"iteration":9,"passed_time":0.1770222058,"remaining_time":17.52519838},
{"learn":[11.43264457],"iteration":10,"passed_time":0.1789160843,"remaining_time":16.08618249},
{"learn":[11.17973129],"iteration":11,"passed_time":0.1811136637,"remaining_time":14.91169164},
{"learn":[10.93746433],"iteration":12,"passed_time":0.1830065499,"remaining_time":13.89442036},
{"learn":[10.69387075],"iteration":13,"passed_time":0.1848597401,"remaining_time":13.01940741},
{"learn":[10.4615922],"iteration":14,"passed_time":0.1862981885,"remaining_time":12.23358104},
{"learn":[10.2299235],"iteration":15,"passed_time":0.1884056717,"remaining_time":11.58694881},
{"learn":[10.01419731],"iteration":16,"passed_time":0.1898473497,"remaining_time":10.97764381},
{"learn":[9.795856918],"iteration":17,"passed_time":0.1910183501,"remaining_time":10.42111221},
{"learn":[9.60040151],"iteration":18,"passed_time":0.1926024292,"remaining_time":9.94436753},
{"learn":[9.418664989],"iteration":19,"passed_time":0.1938551782,"remaining_time":9.498903734},
{"learn":[9.249278645],"iteration":20,"passed_time":0.1949518299,"remaining_time":9.088468642},
{"learn":[9.090113396],"iteration":21,"passed_time":0.1959852037,"remaining_time":8.712433145},
{"learn":[8.909548708],"iteration":22,"passed_time":0.1969999213,"remaining_time":8.368214047},
{"learn":[8.740140208],"iteration":23,"passed_time":0.1979959302,"remaining_time":8.051834495},
{"learn":[8.59377682],"iteration":24,"passed_time":0.1990489386,"remaining_time":7.762908606},
{"learn":[8.453885414],"iteration":25,"passed_time":0.200031433,"remaining_time":7.493485221},
{"learn":[8.317732234],"iteration":26,"passed_time":0.2013125946,"remaining_time":7.254709429},
{"learn":[8.180896085],"iteration":27,"passed_time":0.2028117897,"remaining_time":7.040466413},
{"learn":[8.053220863],"iteration":28,"passed_time":0.2037516368,"remaining_time":6.822166873},
{"learn":[7.924234474],"iteration":29,"passed_time":0.2048735644,"remaining_time":6.624245248},
{"learn":[7.818879511],"iteration":30,"passed_time":0.205811492,"remaining_time":6.433268896},
{"learn":[7.719346395],"iteration":31,"passed_time":0.2068999258,"remaining_time":6.258722755},
{"learn":[7.624163594],"iteration":32,"passed_time":0.2078446432,"remaining_time":6.090477878},
{"learn":[7.524952543],"iteration":33,"passed_time":0.2088204208,"remaining_time":5.93295666},
{"learn":[7.424464745],"iteration":34,"passed_time":0.2096749583,"remaining_time":5.781038136},
{"learn":[7.327482321],"iteration":35,"passed_time":0.2105199294,"remaining_time":5.637255887},
{"learn":[7.238666841],"iteration":36,"passed_time":0.2113114333,"remaining_time":5.499808385},
{"learn":[7.158842395],"iteration":37,"passed_time":0.2121981386,"remaining_time":5.371963403},
{"learn":[7.074348246],"iteration":38,"passed_time":0.2130390424,"remaining_time":5.249500507},
{"learn":[6.992269093],"iteration":39,"passed_time":0.2139311156,"remaining_time":5.134346775},
{"learn":[6.925219745],"iteration":40,"passed_time":0.2151284854,"remaining_time":5.031907745},
{"learn":[6.86013671],"iteration":41,"passed_time":0.215967749,"remaining_time":4.926121513},
{"learn":[6.786739622],"iteration":42,"passed_time":0.2168333312,"remaining_time":4.825802277},
{"learn":[6.73057926],"iteration":43,"passed_time":0.2176320853,"remaining_time":4.728551671},
{"learn":[6.666356486],"iteration":44,"passed_time":0.2186085071,"remaining_time":4.639358317},
{"learn":[6.606182832],"iteration":45,"passed_time":0.2194595712,"remaining_time":4.551400672},
{"learn":[6.547854615],"iteration":46,"passed_time":0.22034993,"remaining_time":4.467946453},
{"learn":[6.49240675],"iteration":47,"passed_time":0.2212310166,"remaining_time":4.387748495},
{"learn":[6.431317261],"iteration":48,"passed_time":0.2221449143,"remaining_time":4.311424766},
{"learn":[6.377586395],"iteration":49,"passed_time":0.2229863182,"remaining_time":4.236740046},
{"learn":[6.327558015],"iteration":50,"passed_time":0.2237735906,"remaining_time":4.163943872},
{"learn":[6.282040317],"iteration":51,"passed_time":0.2245626533,"remaining_time":4.093949909},
{"learn":[6.237655841],"iteration":52,"passed_time":0.2254059941,"remaining_time":4.027537291},
{"learn":[6.192792003],"iteration":53,"passed_time":0.2262603791,"remaining_time":3.963746642},
{"learn":[6.150579347],"iteration":54,"passed_time":0.2284682201,"remaining_time":3.925499418},
{"learn":[6.115693845],"iteration":55,"passed_time":0.2296469287,"remaining_time":3.871191084},
{"learn":[6.078780782],"iteration":56,"passed_time":0.2306121939,"remaining_time":3.815215768},
{"learn":[6.045146957],"iteration":57,"passed_time":0.2319669212,"remaining_time":3.767462755},
{"learn":[6.008080327],"iteration":58,"passed_time":0.2343883219,"remaining_time":3.738295101},
{"learn":[5.977575734],"iteration":59,"passed_time":0.2353076214,"remaining_time":3.686486068},
{"learn":[5.948036502],"iteration":60,"passed_time":0.2361177501,"remaining_time":3.634665039},
{"learn":[5.914888282],"iteration":61,"passed_time":0.2369982662,"remaining_time":3.585554414},
{"learn":[5.884957796],"iteration":62,"passed_time":0.2379891818,"remaining_time":3.539616879},
{"learn":[5.849539885],"iteration":63,"passed_time":0.2388358549,"remaining_time":3.492974377},
{"learn":[5.821387627],"iteration":64,"passed_time":0.2404533928,"remaining_time":3.458829573},
{"learn":[5.797012279],"iteration":65,"passed_time":0.2421086743,"remaining_time":3.426204573},
{"learn":[5.768685095],"iteration":66,"passed_time":0.2429999008,"remaining_time":3.38386429},
{"learn":[5.755484587],"iteration":67,"passed_time":0.2437176501,"remaining_time":3.34036544},
{"learn":[5.731887055],"iteration":68,"passed_time":0.244907245,"remaining_time":3.304473118},
{"learn":[5.707148487],"iteration":69,"passed_time":0.2458799821,"remaining_time":3.266691191},
{"learn":[5.685365039],"iteration":70,"passed_time":0.2467514064,"remaining_time":3.228620514},
{"learn":[5.663541834],"iteration":71,"passed_time":0.2476921795,"remaining_time":3.19247698},
{"learn":[5.638108797],"iteration":72,"passed_time":0.2485468304,"remaining_time":3.156204271},
{"learn":[5.619204893],"iteration":73,"passed_time":0.2492928982,"remaining_time":3.11953005},
{"learn":[5.598472793],"iteration":74,"passed_time":0.2501497544,"remaining_time":3.085180304},
{"learn":[5.577007075],"iteration":75,"passed_time":0.251015382,"remaining_time":3.051818591},
{"learn":[5.562637084],"iteration":76,"passed_time":0.2519662237,"remaining_time":3.020322395},
{"learn":[5.54729991],"iteration":77,"passed_time":0.2527945243,"remaining_time":2.988160916},
{"learn":[5.530737623],"iteration":78,"passed_time":0.2539645471,"remaining_time":2.960776555},
{"learn":[5.513704873],"iteration":79,"passed_time":0.2549364207,"remaining_time":2.931768838},
{"learn":[5.501575529],"iteration":80,"passed_time":0.2558079525,"remaining_time":2.902314918},
{"learn":[5.484080734],"iteration":81,"passed_time":0.2568419743,"remaining_time":2.875377224},
{"learn":[5.472178894],"iteration":82,"passed_time":0.2579544958,"remaining_time":2.849930996},
{"learn":[5.458923342],"iteration":83,"passed_time":0.2588545728,"remaining_time":2.822747484},
{"learn":[5.451382371],"iteration":84,"passed_time":0.2594336678,"remaining_time":2.79272713},
{"learn":[5.441410748],"iteration":85,"passed_time":0.2602780063,"remaining_time":2.76621044},
{"learn":[5.434047468],"iteration":86,"passed_time":0.2608821035,"remaining_time":2.737762765},
{"learn":[5.422107497],"iteration":87,"passed_time":0.2617973644,"remaining_time":2.713172686},
{"learn":[5.40731265],"iteration":88,"passed_time":0.2626199196,"remaining_time":2.688165694},
{"learn":[5.396360181],"iteration":89,"passed_time":0.2634140597,"remaining_time":2.663408826},
{"learn":[5.383793239],"iteration":90,"passed_time":0.2642533816,"remaining_time":2.639629933},
{"learn":[5.369605034],"iteration":91,"passed_time":0.2650916796,"remaining_time":2.616339621},
{"learn":[5.357467333],"iteration":92,"passed_time":0.2662053051,"remaining_time":2.596217331},
{"learn":[5.341109968],"iteration":93,"passed_time":0.2675190113,"remaining_time":2.578427917},
{"learn":[5.330529276],"iteration":94,"passed_time":0.2684570302,"remaining_time":2.557406446},
{"learn":[5.319862075],"iteration":95,"passed_time":0.2693135447,"remaining_time":2.536035879},
{"learn":[5.313052243],"iteration":96,"passed_time":0.2702137025,"remaining_time":2.515494571},
{"learn":[5.299677207],"iteration":97,"passed_time":0.271368533,"remaining_time":2.49769813},
{"learn":[5.287546698],"iteration":98,"passed_time":0.2728343279,"remaining_time":2.483067974},
{"learn":[5.279803754],"iteration":99,"passed_time":0.2737043203,"remaining_time":2.463338883},
{"learn":[5.272254612],"iteration":100,"passed_time":0.2745196661,"remaining_time":2.44349683},
{"learn":[5.268813888],"iteration":101,"passed_time":0.2749639483,"remaining_time":2.420761035},
{"learn":[5.258113767],"iteration":102,"passed_time":0.2758269521,"remaining_time":2.402104622},
{"learn":[5.251018576],"iteration":103,"passed_time":0.2765745735,"remaining_time":2.382796326},
{"learn":[5.24171237],"iteration":104,"passed_time":0.2774668143,"remaining_time":2.365074274},
{"learn":[5.233984943],"iteration":105,"passed_time":0.278397885,"remaining_time":2.347997257},
{"learn":[5.226240449],"iteration":106,"passed_time":0.2795706553,"remaining_time":2.333239207},
{"learn":[5.220541644],"iteration":107,"passed_time":0.2806045416,"remaining_time":2.317585659},
{"learn":[5.211712096],"iteration":108,"passed_time":0.2818301899,"remaining_time":2.303767882},
{"learn":[5.203388597],"iteration":109,"passed_time":0.2829014756,"remaining_time":2.288930121},
{"learn":[5.196026544],"iteration":110,"passed_time":0.2840485999,"remaining_time":2.274947796},
{"learn":[5.188716772],"iteration":111,"passed_time":0.285054242,"remaining_time":2.260072919},
{"learn":[5.182163132],"iteration":112,"passed_time":0.285993872,"remaining_time":2.244925349},
{"learn":[5.17764747],"iteration":113,"passed_time":0.2868225398,"remaining_time":2.229164651},
{"learn":[5.170548056],"iteration":114,"passed_time":0.2876412807,"remaining_time":2.213587247},
{"learn":[5.165901827],"iteration":115,"passed_time":0.2883121088,"remaining_time":2.197137105},
{"learn":[5.160333668],"iteration":116,"passed_time":0.2891920702,"remaining_time":2.182535025},
{"learn":[5.148953243],"iteration":117,"passed_time":0.2900311004,"remaining_time":2.167859581},
{"learn":[5.144729126],"iteration":118,"passed_time":0.2906991281,"remaining_time":2.152150688},
{"learn":[5.139939946],"iteration":119,"passed_time":0.2915369835,"remaining_time":2.137937879},
{"learn":[5.132898872],"iteration":120,"passed_time":0.2925634483,"remaining_time":2.12531629},
{"learn":[5.129073077],"iteration":121,"passed_time":0.2937427679,"remaining_time":2.113984838},
{"learn":[5.127123916],"iteration":122,"passed_time":0.2942548511,"remaining_time":2.098061012},
{"learn":[5.121282057],"iteration":123,"passed_time":0.2950282331,"remaining_time":2.084231711},
{"learn":[5.114489821],"iteration":124,"passed_time":0.2960709049,"remaining_time":2.072496334},
{"learn":[5.107777291],"iteration":125,"passed_time":0.2971119127,"remaining_time":2.060919141},
{"learn":[5.103518754],"iteration":126,"passed_time":0.2980886071,"remaining_time":2.04906578},
{"learn":[5.101133351],"iteration":127,"passed_time":0.2987364146,"remaining_time":2.035141825},
{"learn":[5.096462705],"iteration":128,"passed_time":0.2995514721,"remaining_time":2.022552962},
{"learn":[5.08562082],"iteration":129,"passed_time":0.3004503871,"remaining_time":2.010706437},
{"learn":[5.080483682],"iteration":130,"passed_time":0.3013610523,"remaining_time":1.999104996},
{"learn":[5.07437499],"iteration":131,"passed_time":0.302264261,"remaining_time":1.987616504},
{"learn":[5.070683732],"iteration":132,"passed_time":0.3030248018,"remaining_time":1.975357167},
{"learn":[5.06432037],"iteration":133,"passed_time":0.3038259547,"remaining_time":1.963531916},
{"learn":[5.057436484],"iteration":134,"passed_time":0.3046987341,"remaining_time":1.952328926},
{"learn":[5.053254656],"iteration":135,"passed_time":0.3056367126,"remaining_time":1.941692057},
{"learn":[5.04801663],"iteration":136,"passed_time":0.3069073052,"remaining_time":1.933292003},
{"learn":[5.045680836],"iteration":137,"passed_time":0.3076938833,"remaining_time":1.921971938},
{"learn":[5.041857933],"iteration":138,"passed_time":0.3086307424,"remaining_time":1.911734311},
{"learn":[5.035264888],"iteration":139,"passed_time":0.3096674659,"remaining_time":1.902243005},
{"learn":[5.028771948],"iteration":140,"passed_time":0.3105572988,"remaining_time":1.891976735},
{"learn":[5.024912247],"iteration":141,"passed_time":0.3114675789,"remaining_time":1.881966075},
{"learn":[5.02239068],"iteration":142,"passed_time":0.3123076626,"remaining_time":1.871662006},
{"learn":[5.017110572],"iteration":143,"passed_time":0.3132372915,"remaining_time":1.862021677},
{"learn":[5.010707886],"iteration":144,"passed_time":0.3141626064,"remaining_time":1.852476059},
{"learn":[5.004389868],"iteration":145,"passed_time":0.3150592995,"remaining_time":1.842881108},
{"learn":[4.997628683],"iteration":146,"passed_time":0.315951937,"remaining_time":1.833380968},
{"learn":[4.991497851],"iteration":147,"passed_time":0.3168469127,"remaining_time":1.824010606},
{"learn":[4.988345253],"iteration":148,"passed_time":0.3177159667,"remaining_time":1.814605957},
{"learn":[4.98460423],"iteration":149,"passed_time":0.3192155097,"remaining_time":1.808887888},
{"learn":[4.982441783],"iteration":150,"passed_time":0.3204554597,"remaining_time":1.801766127},
{"learn":[4.977461771],"iteration":151,"passed_time":0.3214628799,"remaining_time":1.793424488},
{"learn":[4.973601586],"iteration":152,"passed_time":0.322371954,"remaining_time":1.784634281},
{"learn":[4.968328804],"iteration":153,"passed_time":0.3233767401,"remaining_time":1.776472222},
{"learn":[4.9640736],"iteration":154,"passed_time":0.3242253255,"remaining_time":1.767550968},
{"learn":[4.960865882],"iteration":155,"passed_time":0.3251611871,"remaining_time":1.759205397},
{"learn":[4.957014156],"iteration":156,"passed_time":0.3262043435,"remaining_time":1.751530329},
{"learn":[4.952244852],"iteration":157,"passed_time":0.3271187306,"remaining_time":1.743252982},
{"learn":[4.949695675],"iteration":158,"passed_time":0.327917248,"remaining_time":1.734455381},
{"learn":[4.946584698],"iteration":159,"passed_time":0.3287786799,"remaining_time":1.726088069},
{"learn":[4.940192834],"iteration":160,"passed_time":0.3296487556,"remaining_time":1.717859043},
{"learn":[4.936727994],"iteration":161,"passed_time":0.3305980346,"remaining_time":1.710130574},
{"learn":[4.932342063],"iteration":162,"passed_time":0.3314801105,"remaining_time":1.702140199},
{"learn":[4.925830838],"iteration":163,"passed_time":0.3324849112,"remaining_time":1.694862108},
{"learn":[4.922571773],"iteration":164,"passed_time":0.3334257292,"remaining_time":1.687336266},
{"learn":[4.918395814],"iteration":165,"passed_time":0.3343153221,"remaining_time":1.679632401},
{"learn":[4.911142452],"iteration":166,"passed_time":0.3351401627,"remaining_time":1.671687159},
{"learn":[4.908276131],"iteration":167,"passed_time":0.3366017745,"remaining_time":1.666980217},
{"learn":[4.904584645],"iteration":168,"passed_time":0.3375524191,"remaining_time":1.659799173},
{"learn":[4.89795517],"iteration":169,"passed_time":0.338424761,"remaining_time":1.652309127},
{"learn":[4.895556491],"iteration":170,"passed_time":0.3393108517,"remaining_time":1.644963135},
{"learn":[4.890591233],"iteration":171,"passed_time":0.3401781945,"remaining_time":1.637602006},
{"learn":[4.884629277],"iteration":172,"passed_time":0.3411655042,"remaining_time":1.630889433},
{"learn":[4.880550786],"iteration":173,"passed_time":0.3420742574,"remaining_time":1.623869751},
{"learn":[4.876384842],"iteration":174,"passed_time":0.342897111,"remaining_time":1.616514952},
{"learn":[4.872638238],"iteration":175,"passed_time":0.3437626986,"remaining_time":1.609434452},
{"learn":[4.869137118],"iteration":176,"passed_time":0.3447626894,"remaining_time":1.603049115},
{"learn":[4.863587157],"iteration":177,"passed_time":0.3462684691,"remaining_time":1.599060009},
{"learn":[4.858028614],"iteration":178,"passed_time":0.3471937266,"remaining_time":1.592436031},
{"learn":[4.853838176],"iteration":179,"passed_time":0.3480027472,"remaining_time":1.585345848},
{"learn":[4.853462329],"iteration":180,"passed_time":0.3486282335,"remaining_time":1.577494603},
{"learn":[4.851573196],"iteration":181,"passed_time":0.3508571922,"remaining_time":1.576929578},
{"learn":[4.848442087],"iteration":182,"passed_time":0.3517614873,"remaining_time":1.570432432},
{"learn":[4.845547104],"iteration":183,"passed_time":0.3528550801,"remaining_time":1.564835573},
{"learn":[4.839868817],"iteration":184,"passed_time":0.3538530444,"remaining_time":1.558866114},
{"learn":[4.836336958],"iteration":185,"passed_time":0.3549414223,"remaining_time":1.553345794},
{"learn":[4.831124789],"iteration":186,"passed_time":0.3558001338,"remaining_time":1.546874378},
{"learn":[4.827407333],"iteration":187,"passed_time":0.3566873429,"remaining_time":1.540585758},
{"learn":[4.824088918],"iteration":188,"passed_time":0.3575149735,"remaining_time":1.534098643},
{"learn":[4.820934539],"iteration":189,"passed_time":0.358657698,"remaining_time":1.529014397},
{"learn":[4.816975227],"iteration":190,"passed_time":0.3596340023,"remaining_time":1.523266533},
{"learn":[4.812340486],"iteration":191,"passed_time":0.360584351,"remaining_time":1.517459144},
{"learn":[4.806402747],"iteration":192,"passed_time":0.361465585,"remaining_time":1.511413094},
{"learn":[4.801521788],"iteration":193,"passed_time":0.3625481687,"remaining_time":1.506256825},
{"learn":[4.797601172],"iteration":194,"passed_time":0.3633501358,"remaining_time":1.499983894},
{"learn":[4.792694629],"iteration":195,"passed_time":0.3642701891,"remaining_time":1.494251184},
{"learn":[4.789794613],"iteration":196,"passed_time":0.3653236368,"remaining_time":1.489111068},
{"learn":[4.785367055],"iteration":197,"passed_time":0.3661752247,"remaining_time":1.483194597},
{"learn":[4.780376856],"iteration":198,"passed_time":0.3670894638,"remaining_time":1.477581208},
{"learn":[4.776691261],"iteration":199,"passed_time":0.3679587686,"remaining_time":1.471835074},
{"learn":[4.773470753],"iteration":200,"passed_time":0.368743193,"remaining_time":1.465800056},
{"learn":[4.77207327],"iteration":201,"passed_time":0.3695919989,"remaining_time":1.460071362},
{"learn":[4.767347177],"iteration":202,"passed_time":0.3705450101,"remaining_time":1.454799867},
{"learn":[4.763983068],"iteration":203,"passed_time":0.3714562495,"remaining_time":1.449407719},
{"learn":[4.761588849],"iteration":204,"passed_time":0.3726575812,"remaining_time":1.445184278},
{"learn":[4.758558086],"iteration":205,"passed_time":0.3735312666,"remaining_time":1.439727309},
{"learn":[4.753678804],"iteration":206,"passed_time":0.3743667346,"remaining_time":1.434168215},
{"learn":[4.746510889],"iteration":207,"passed_time":0.3756997174,"remaining_time":1.430548924},
{"learn":[4.744840601],"iteration":208,"passed_time":0.3766301498,"remaining_time":1.425427983},
{"learn":[4.741702222],"iteration":209,"passed_time":0.3774807909,"remaining_time":1.420046785},
{"learn":[4.739352853],"iteration":210,"passed_time":0.3783081327,"remaining_time":1.414621406},
{"learn":[4.735539287],"iteration":211,"passed_time":0.3791079895,"remaining_time":1.409137244},
{"learn":[4.730726751],"iteration":212,"passed_time":0.3799491066,"remaining_time":1.403849516},
{"learn":[4.726416092],"iteration":213,"passed_time":0.3809632462,"remaining_time":1.399238839},
{"learn":[4.721293082],"iteration":214,"passed_time":0.3818623214,"remaining_time":1.394241499},
{"learn":[4.718443695],"iteration":215,"passed_time":0.3826691484,"remaining_time":1.388947279},
{"learn":[4.711627962],"iteration":216,"passed_time":0.3837671531,"remaining_time":1.384745073},
{"learn":[4.709790764],"iteration":217,"passed_time":0.3850437387,"remaining_time":1.381211943},
{"learn":[4.706913073],"iteration":218,"passed_time":0.3862230733,"remaining_time":1.377352604},
{"learn":[4.703846389],"iteration":219,"passed_time":0.3872014891,"remaining_time":1.37280528},
{"learn":[4.701001135],"iteration":220,"passed_time":0.3882327288,"remaining_time":1.368476451},
{"learn":[4.700380864],"iteration":221,"passed_time":0.3891375273,"remaining_time":1.363734217},
{"learn":[4.695837486],"iteration":222,"passed_time":0.3902614806,"remaining_time":1.359790002},
{"learn":[4.691242996],"iteration":223,"passed_time":0.391285698,"remaining_time":1.355525454},
{"learn":[4.690284609],"iteration":224,"passed_time":0.3922536043,"remaining_time":1.351095748},
{"learn":[4.68827119],"iteration":225,"passed_time":0.3931880306,"remaining_time":1.346582016},
{"learn":[4.686922425],"iteration":226,"passed_time":0.3940367865,"remaining_time":1.341808088},
{"learn":[4.686085874],"iteration":227,"passed_time":0.3949052703,"remaining_time":1.337135389},
{"learn":[4.683230741],"iteration":228,"passed_time":0.3961006423,"remaining_time":1.333596486},
{"learn":[4.6773487],"iteration":229,"passed_time":0.3969962877,"remaining_time":1.329074528},
{"learn":[4.671462906],"iteration":230,"passed_time":0.3980358737,"remaining_time":1.325063147},
{"learn":[4.664799601],"iteration":231,"passed_time":0.3989562912,"remaining_time":1.320682895},
{"learn":[4.660979386],"iteration":232,"passed_time":0.3998925019,"remaining_time":1.31638433},
{"learn":[4.656281279],"iteration":233,"passed_time":0.4008978335,"remaining_time":1.312340771},
{"learn":[4.651997094],"iteration":234,"passed_time":0.4021988465,"remaining_time":1.309285607},
{"learn":[4.650151977],"iteration":235,"passed_time":0.4030300038,"remaining_time":1.30472425},
{"learn":[4.648478046],"iteration":236,"passed_time":0.4039131224,"remaining_time":1.300361656},
{"learn":[4.646364602],"iteration":237,"passed_time":0.4047642444,"remaining_time":1.295925858},
{"learn":[4.642635873],"iteration":238,"passed_time":0.4056526646,"remaining_time":1.291638819},
{"learn":[4.640860821],"iteration":239,"passed_time":0.4066158286,"remaining_time":1.28761679},
{"learn":[4.639446822],"iteration":240,"passed_time":0.4073931411,"remaining_time":1.28303483},
{"learn":[4.637120072],"iteration":241,"passed_time":0.408273115,"remaining_time":1.278805873},
{"learn":[4.633769267],"iteration":242,"passed_time":0.4090659624,"remaining_time":1.27433306},
{"learn":[4.630491517],"iteration":243,"passed_time":0.409907768,"remaining_time":1.270042101},
{"learn":[4.627813333],"iteration":244,"passed_time":0.4115086476,"remaining_time":1.268118485},
{"learn":[4.622496304],"iteration":245,"passed_time":0.4125984449,"remaining_time":1.264631006},
{"learn":[4.618979301],"iteration":246,"passed_time":0.4135005271,"remaining_time":1.260590676},
{"learn":[4.616563458],"iteration":247,"passed_time":0.4145002354,"remaining_time":1.256871681},
{"learn":[4.614759385],"iteration":248,"passed_time":0.4156179819,"remaining_time":1.25353054},
{"learn":[4.61251363],"iteration":249,"passed_time":0.4166179543,"remaining_time":1.249853863},
{"learn":[4.608796693],"iteration":250,"passed_time":0.4174895061,"remaining_time":1.245815299},
{"learn":[4.60847774],"iteration":251,"passed_time":0.4183001962,"remaining_time":1.241621217},
{"learn":[4.605195659],"iteration":252,"passed_time":0.4191895749,"remaining_time":1.237686215},
{"learn":[4.60103766],"iteration":253,"passed_time":0.4200898235,"remaining_time":1.233807119},
{"learn":[4.599325598],"iteration":254,"passed_time":0.4210407031,"remaining_time":1.230099309},
{"learn":[4.597012808],"iteration":255,"passed_time":0.4219347141,"remaining_time":1.226247763},
{"learn":[4.594161533],"iteration":256,"passed_time":0.4228040706,"remaining_time":1.222347955},
{"learn":[4.592197259],"iteration":257,"passed_time":0.423845431,"remaining_time":1.218966317},
{"learn":[4.58952828],"iteration":258,"passed_time":0.4249467879,"remaining_time":1.215774401},
{"learn":[4.585816572],"iteration":259,"passed_time":0.4259025162,"remaining_time":1.212184085},
{"learn":[4.582934052],"iteration":260,"passed_time":0.4268232396,"remaining_time":1.208514843},
{"learn":[4.582234842],"iteration":261,"passed_time":0.427867352,"remaining_time":1.205214144},
{"learn":[4.57571562],"iteration":262,"passed_time":0.4288490063,"remaining_time":1.20175558},
{"learn":[4.571197349],"iteration":263,"passed_time":0.4298151157,"remaining_time":1.198272444},
{"learn":[4.56723703],"iteration":264,"passed_time":0.4307240336,"remaining_time":1.194649678},
{"learn":[4.560335567],"iteration":265,"passed_time":0.431611622,"remaining_time":1.190988461},
{"learn":[4.554709345],"iteration":266,"passed_time":0.4324402898,"remaining_time":1.187186264},
{"learn":[4.552806306],"iteration":267,"passed_time":0.4333381597,"remaining_time":1.183595272},
{"learn":[4.550766241],"iteration":268,"passed_time":0.43434563,"remaining_time":1.180322139},
{"learn":[4.549216045],"iteration":269,"passed_time":0.4352139838,"remaining_time":1.17668966},
{"learn":[4.547687452],"iteration":270,"passed_time":0.4361446953,"remaining_time":1.173245324},
{"learn":[4.545642435],"iteration":271,"passed_time":0.4372096385,"remaining_time":1.170178738},
{"learn":[4.543930359],"iteration":272,"passed_time":0.4382170125,"remaining_time":1.166973509},
{"learn":[4.541029943],"iteration":273,"passed_time":0.4391038636,"remaining_time":1.163464982},
{"learn":[4.537781449],"iteration":274,"passed_time":0.4399869718,"remaining_time":1.159965653},
{"learn":[4.53066128],"iteration":275,"passed_time":0.4410133749,"remaining_time":1.156861172},
{"learn":[4.526763956],"iteration":276,"passed_time":0.4419717998,"remaining_time":1.153594264},
{"learn":[4.522036004],"iteration":277,"passed_time":0.4431869386,"remaining_time":1.151010682},
{"learn":[4.515307629],"iteration":278,"passed_time":0.4441776938,"remaining_time":1.147857051},
{"learn":[4.51109143],"iteration":279,"passed_time":0.4451248437,"remaining_time":1.144606741},
{"learn":[4.508233494],"iteration":280,"passed_time":0.4459774151,"remaining_time":1.141130824},
{"learn":[4.502555629],"iteration":281,"passed_time":0.4468194516,"remaining_time":1.137646689},
{"learn":[4.500081355],"iteration":282,"passed_time":0.4477374379,"remaining_time":1.13437365},
{"learn":[4.495281743],"iteration":283,"passed_time":0.4487529085,"remaining_time":1.131362967},
{"learn":[4.492138869],"iteration":284,"passed_time":0.4495330473,"remaining_time":1.127775891},
{"learn":[4.491708261],"iteration":285,"passed_time":0.4506816143,"remaining_time":1.125128226},
{"learn":[4.489398865],"iteration":286,"passed_time":0.4516712815,"remaining_time":1.12209625},
{"learn":[4.485796373],"iteration":287,"passed_time":0.4526678534,"remaining_time":1.119095527},
{"learn":[4.479542205],"iteration":288,"passed_time":0.4535810165,"remaining_time":1.11590347},
{"learn":[4.475986993],"iteration":289,"passed_time":0.4546772906,"remaining_time":1.113175436},
{"learn":[4.468661855],"iteration":290,"passed_time":0.4555761678,"remaining_time":1.109977673},
{"learn":[4.463785664],"iteration":291,"passed_time":0.4566336556,"remaining_time":1.107180233},
{"learn":[4.460445831],"iteration":292,"passed_time":0.4575533301,"remaining_time":1.104062131},
{"learn":[4.45692492],"iteration":293,"passed_time":0.4584816746,"remaining_time":1.100979804},
{"learn":[4.454031688],"iteration":294,"passed_time":0.4593931708,"remaining_time":1.097871815},
{"learn":[4.451672391],"iteration":295,"passed_time":0.4602824969,"remaining_time":1.094725939},
{"learn":[4.45031553],"iteration":296,"passed_time":0.4611498889,"remaining_time":1.09154334},
{"learn":[4.446782666],"iteration":297,"passed_time":0.4621888515,"remaining_time":1.088780449},
{"learn":[4.444369689],"iteration":298,"passed_time":0.4630764607,"remaining_time":1.085674244},
{"learn":[4.44411683],"iteration":299,"passed_time":0.464033262,"remaining_time":1.082744278},
{"learn":[4.440876943],"iteration":300,"passed_time":0.4651446955,"remaining_time":1.080186519},
{"learn":[4.439336453],"iteration":301,"passed_time":0.4660995732,"remaining_time":1.077276497},
{"learn":[4.436666901],"iteration":302,"passed_time":0.4680201945,"remaining_time":1.076600909},
{"learn":[4.433043336],"iteration":303,"passed_time":0.4689876128,"remaining_time":1.073734798},
{"learn":[4.431419305],"iteration":304,"passed_time":0.4698327031,"remaining_time":1.070602389},
{"learn":[4.428859646],"iteration":305,"passed_time":0.4707028705,"remaining_time":1.067541804},
{"learn":[4.424552441],"iteration":306,"passed_time":0.4715964265,"remaining_time":1.064548285},
{"learn":[4.422706391],"iteration":307,"passed_time":0.4726305483,"remaining_time":1.061884219},
{"learn":[4.421427994],"iteration":308,"passed_time":0.4734827838,"remaining_time":1.05882396},
{"learn":[4.418733158],"iteration":309,"passed_time":0.4743174692,"remaining_time":1.055738883},
{"learn":[4.415656941],"iteration":310,"passed_time":0.4751634346,"remaining_time":1.052693268},
{"learn":[4.410747417],"iteration":311,"passed_time":0.476027792,"remaining_time":1.049702311},
{"learn":[4.408126521],"iteration":312,"passed_time":0.4775233881,"remaining_time":1.04811044},
{"learn":[4.407843853],"iteration":313,"passed_time":0.4784621709,"remaining_time":1.045302705},
{"learn":[4.405219398],"iteration":314,"passed_time":0.479368883,"remaining_time":1.042437095},
{"learn":[4.402708465],"iteration":315,"passed_time":0.4803786053,"remaining_time":1.039806855},
{"learn":[4.40104971],"iteration":316,"passed_time":0.4814279173,"remaining_time":1.037272137},
{"learn":[4.400830038],"iteration":317,"passed_time":0.4827135767,"remaining_time":1.035253646},
{"learn":[4.39784288],"iteration":318,"passed_time":0.4836750479,"remaining_time":1.032547673},
{"learn":[4.393741845],"iteration":319,"passed_time":0.4845004861,"remaining_time":1.029563533},
{"learn":[4.393425936],"iteration":320,"passed_time":0.4853254325,"remaining_time":1.026591803},
{"learn":[4.390505974],"iteration":321,"passed_time":0.4862097412,"remaining_time":1.023758399},
{"learn":[4.390305136],"iteration":322,"passed_time":0.4870343605,"remaining_time":1.020811957},
{"learn":[4.38568203],"iteration":323,"passed_time":0.4880201745,"remaining_time":1.018214932},
{"learn":[4.383057135],"iteration":324,"passed_time":0.4889115118,"remaining_time":1.015431601},
{"learn":[4.380662684],"iteration":325,"passed_time":0.4898739399,"remaining_time":1.012806857},
{"learn":[4.37805727],"iteration":326,"passed_time":0.4910492909,"remaining_time":1.010630498},
{"learn":[4.373708319],"iteration":327,"passed_time":0.4920377596,"remaining_time":1.008077361},
{"learn":[4.36887921],"iteration":328,"passed_time":0.4930109109,"remaining_time":1.005502496},
{"learn":[4.367895929],"iteration":329,"passed_time":0.494130476,"remaining_time":1.003234603},
{"learn":[4.362140573],"iteration":330,"passed_time":0.4950310584,"remaining_time":1.000531052},
{"learn":[4.361931924],"iteration":331,"passed_time":0.4959112865,"remaining_time":0.9977974078},
{"learn":[4.359656377],"iteration":332,"passed_time":0.4968365852,"remaining_time":0.9951651721},
{"learn":[4.354281355],"iteration":333,"passed_time":0.4976978771,"remaining_time":0.9924155274},
{"learn":[4.348589447],"iteration":334,"passed_time":0.4985694456,"remaining_time":0.9896975561},
{"learn":[4.346355698],"iteration":335,"passed_time":0.4994273103,"remaining_time":0.9869634941},
{"learn":[4.343894047],"iteration":336,"passed_time":0.5002651186,"remaining_time":0.9842011088},
{"learn":[4.341561356],"iteration":337,"passed_time":0.5010395574,"remaining_time":0.981325997},
{"learn":[4.338869061],"iteration":338,"passed_time":0.5019338997,"remaining_time":0.9786970729},
{"learn":[4.333720063],"iteration":339,"passed_time":0.502855227,"remaining_time":0.9761307347},
{"learn":[4.330892223],"iteration":340,"passed_time":0.5040522475,"remaining_time":0.9741068362},
{"learn":[4.328311474],"iteration":341,"passed_time":0.504957727,"remaining_time":0.9715268548},
{"learn":[4.324580133],"iteration":342,"passed_time":0.5058432209,"remaining_time":0.968918356},
{"learn":[4.323354432],"iteration":343,"passed_time":0.5070878641,"remaining_time":0.967004764},
{"learn":[4.323159553],"iteration":344,"passed_time":0.5081946631,"remaining_time":0.9648333459},
{"learn":[4.318639682],"iteration":345,"passed_time":0.5091766116,"remaining_time":0.9624320924},
{"learn":[4.312712208],"iteration":346,"passed_time":0.5100846472,"remaining_time":0.9598999269},
{"learn":[4.311461062],"iteration":347,"passed_time":0.5110715698,"remaining_time":0.9575248951},
{"learn":[4.311178356],"iteration":348,"passed_time":0.5119652087,"remaining_time":0.9549838133},
{"learn":[4.311102505],"iteration":349,"passed_time":0.5128596756,"remaining_time":0.9524536832},
{"learn":[4.310232308],"iteration":350,"passed_time":0.5136905779,"remaining_time":0.949815342},
{"learn":[4.305128197],"iteration":351,"passed_time":0.514553315,"remaining_time":0.9472458754},
{"learn":[4.304595496],"iteration":352,"passed_time":0.5155206821,"remaining_time":0.9448778508},
{"learn":[4.3004992],"iteration":353,"passed_time":0.5170814694,"remaining_time":0.9436006475},
{"learn":[4.297581524],"iteration":354,"passed_time":0.5180349794,"remaining_time":0.9412184837},
{"learn":[4.297355825],"iteration":355,"passed_time":0.5188435542,"remaining_time":0.9385821598},
{"learn":[4.295758715],"iteration":356,"passed_time":0.5198360655,"remaining_time":0.9362873673},
{"learn":[4.292500657],"iteration":357,"passed_time":0.5209332739,"remaining_time":0.9341876029},
{"learn":[4.290797586],"iteration":358,"passed_time":0.5219808061,"remaining_time":0.9320047261},
{"learn":[4.286410608],"iteration":359,"passed_time":0.5229298233,"remaining_time":0.9296530192},
{"learn":[4.280278245],"iteration":360,"passed_time":0.5237730842,"remaining_time":0.9271218858},
{"learn":[4.279941283],"iteration":361,"passed_time":0.5246377191,"remaining_time":0.924637748},
{"learn":[4.274426275],"iteration":362,"passed_time":0.5254515863,"remaining_time":0.9220734448},
{"learn":[4.273567658],"iteration":363,"passed_time":0.5263377936,"remaining_time":0.9196451559},
{"learn":[4.269488271],"iteration":364,"passed_time":0.5272649759,"remaining_time":0.9172966019},
{"learn":[4.266838205],"iteration":365,"passed_time":0.5281862269,"remaining_time":0.9149455406},
{"learn":[4.263456509],"iteration":366,"passed_time":0.5292729725,"remaining_time":0.9128877155},
{"learn":[4.260360204],"iteration":367,"passed_time":0.5305541283,"remaining_time":0.9111690464},
{"learn":[4.255120549],"iteration":368,"passed_time":0.5315030559,"remaining_time":0.9088846295},
{"learn":[4.252582211],"iteration":369,"passed_time":0.5324330041,"remaining_time":0.906575115},
{"learn":[4.247857931],"iteration":370,"passed_time":0.5334911266,"remaining_time":0.9044903466},
{"learn":[4.245288911],"iteration":371,"passed_time":0.5343775389,"remaining_time":0.9021212216},
{"learn":[4.24048515],"iteration":372,"passed_time":0.535434968,"remaining_time":0.9000475199},
{"learn":[4.2378365],"iteration":373,"passed_time":0.5364257882,"remaining_time":0.8978677632},
{"learn":[4.236751063],"iteration":374,"passed_time":0.5372973208,"remaining_time":0.8954955347},
{"learn":[4.233240093],"iteration":375,"passed_time":0.5382362495,"remaining_time":0.8932431375},
{"learn":[4.230358421],"iteration":376,"passed_time":0.5391154424,"remaining_time":0.8908989937},
{"learn":[4.225853583],"iteration":377,"passed_time":0.5399522498,"remaining_time":0.8884928555},
{"learn":[4.224702126],"iteration":378,"passed_time":0.5408131279,"remaining_time":0.8861344391},
{"learn":[4.224361982],"iteration":379,"passed_time":0.5417541789,"remaining_time":0.883914713},
{"learn":[4.223787954],"iteration":380,"passed_time":0.5427743124,"remaining_time":0.881830182},
{"learn":[4.22144054],"iteration":381,"passed_time":0.5688131439,"remaining_time":0.9202264999},
{"learn":[4.217739335],"iteration":382,"passed_time":0.5760951059,"remaining_time":0.9280696614},
{"learn":[4.215611665],"iteration":383,"passed_time":0.5774744132,"remaining_time":0.9263652045},
{"learn":[4.210236863],"iteration":384,"passed_time":0.5797540887,"remaining_time":0.9261006872},
{"learn":[4.208454294],"iteration":385,"passed_time":0.581813381,"remaining_time":0.9254751708},
{"learn":[4.207446501],"iteration":386,"passed_time":0.582931275,"remaining_time":0.9233510893},
{"learn":[4.204985442],"iteration":387,"passed_time":0.5837926853,"remaining_time":0.9208276376},
{"learn":[4.202796622],"iteration":388,"passed_time":0.5849836162,"remaining_time":0.9188303072},
{"learn":[4.199774004],"iteration":389,"passed_time":0.5858945227,"remaining_time":0.9163991252},
{"learn":[4.199458358],"iteration":390,"passed_time":0.5867820398,"remaining_time":0.9139392896},
{"learn":[4.19751254],"iteration":391,"passed_time":0.5876012374,"remaining_time":0.9113815111},
{"learn":[4.195201346],"iteration":392,"passed_time":0.5905138082,"remaining_time":0.9120658565},
{"learn":[4.190593508],"iteration":393,"passed_time":0.5915916229,"remaining_time":0.909909958},
{"learn":[4.187212054],"iteration":394,"passed_time":0.5924845387,"remaining_time":0.9074763188},
{"learn":[4.184984466],"iteration":395,"passed_time":0.5934577192,"remaining_time":0.9051728849},
{"learn":[4.182832144],"iteration":396,"passed_time":0.5945631935,"remaining_time":0.9030770924},
{"learn":[4.179752812],"iteration":397,"passed_time":0.5966680459,"remaining_time":0.9024978986},
{"learn":[4.17878934],"iteration":398,"passed_time":0.5974694121,"remaining_time":0.8999476608},
{"learn":[4.174548229],"iteration":399,"passed_time":0.5983039683,"remaining_time":0.8974559524},
{"learn":[4.168872556],"iteration":400,"passed_time":0.6063011813,"remaining_time":0.9056718394},
{"learn":[4.163926494],"iteration":401,"passed_time":0.6077633803,"remaining_time":0.9040858245},
{"learn":[4.159485076],"iteration":402,"passed_time":0.6090930914,"remaining_time":0.9023041577},
{"learn":[4.155926102],"iteration":403,"passed_time":0.6101208356,"remaining_time":0.9000792525},
{"learn":[4.153540115],"iteration":404,"passed_time":0.6112894277,"remaining_time":0.8980671839},
{"learn":[4.150983044],"iteration":405,"passed_time":0.6124109077,"remaining_time":0.8959903428},
{"learn":[4.146539132],"iteration":406,"passed_time":0.6139574132,"remaining_time":0.8945374595},
{"learn":[4.144869174],"iteration":407,"passed_time":0.6147729807,"remaining_time":0.8920235406},
{"learn":[4.142825962],"iteration":408,"passed_time":0.6160467416,"remaining_time":0.8901800105},
{"learn":[4.142467378],"iteration":409,"passed_time":0.6168919832,"remaining_time":0.88772261},
{"learn":[4.141800768],"iteration":410,"passed_time":0.6177582929,"remaining_time":0.8853032471},
{"learn":[4.140107084],"iteration":411,"passed_time":0.6185991738,"remaining_time":0.8828551316},
{"learn":[4.136243196],"iteration":412,"passed_time":0.6195191046,"remaining_time":0.8805271535},
{"learn":[4.133618439],"iteration":413,"passed_time":0.6203881143,"remaining_time":0.878133901},
{"learn":[4.131053025],"iteration":414,"passed_time":0.6212520858,"remaining_time":0.8757408921},
{"learn":[4.128379975],"iteration":415,"passed_time":0.6221434602,"remaining_time":0.8733937037},
{"learn":[4.127068571],"iteration":416,"passed_time":0.6229940196,"remaining_time":0.8709964351},
{"learn":[4.125969877],"iteration":417,"passed_time":0.6241840913,"remaining_time":0.869079285},
{"learn":[4.123893633],"iteration":418,"passed_time":0.6251071304,"remaining_time":0.8667953288},
{"learn":[4.119643722],"iteration":419,"passed_time":0.6259617538,"remaining_time":0.8644233743},
{"learn":[4.11465686],"iteration":420,"passed_time":0.6268834198,"remaining_time":0.8621508316},
{"learn":[4.111565986],"iteration":421,"passed_time":0.6283864338,"remaining_time":0.8606809449},
{"learn":[4.106322452],"iteration":422,"passed_time":0.6295549496,"remaining_time":0.858754624},
{"learn":[4.104222175],"iteration":423,"passed_time":0.6304526846,"remaining_time":0.8564640243},
{"learn":[4.103008002],"iteration":424,"passed_time":0.6313183655,"remaining_time":0.8541366121},
{"learn":[4.099176337],"iteration":425,"passed_time":0.6321589617,"remaining_time":0.851782263},
{"learn":[4.096525716],"iteration":426,"passed_time":0.6331388382,"remaining_time":0.8496219071},
{"learn":[4.094967724],"iteration":427,"passed_time":0.634129073,"remaining_time":0.8474809106},
{"learn":[4.094683584],"iteration":428,"passed_time":0.6349623081,"remaining_time":0.8451363122},
{"learn":[4.091096563],"iteration":429,"passed_time":0.6360915335,"remaining_time":0.8431911025},
{"learn":[4.089178677],"iteration":430,"passed_time":0.6375219885,"remaining_time":0.8416473584},
{"learn":[4.085335077],"iteration":431,"passed_time":0.638611775,"remaining_time":0.8396562227},
{"learn":[4.084852122],"iteration":432,"passed_time":0.6395402504,"remaining_time":0.8374580184},
{"learn":[4.080322952],"iteration":433,"passed_time":0.6406624509,"remaining_time":0.8355183115},
{"learn":[4.077449519],"iteration":434,"passed_time":0.6415458507,"remaining_time":0.8332721969},
{"learn":[4.076568374],"iteration":435,"passed_time":0.6426331256,"remaining_time":0.8312960615},
{"learn":[4.076071793],"iteration":436,"passed_time":0.6435135008,"remaining_time":0.8290574392},
{"learn":[4.075027644],"iteration":437,"passed_time":0.6444363887,"remaining_time":0.8268795672},
{"learn":[4.07020837],"iteration":438,"passed_time":0.6453630896,"remaining_time":0.8247122854},
{"learn":[4.06833694],"iteration":439,"passed_time":0.6461814384,"remaining_time":0.8224127397},
{"learn":[4.063936568],"iteration":440,"passed_time":0.6471250815,"remaining_time":0.8202787314},
{"learn":[4.061734926],"iteration":441,"passed_time":0.6482414461,"remaining_time":0.8183681605},
{"learn":[4.060815619],"iteration":442,"passed_time":0.649094188,"remaining_time":0.8161297126},
{"learn":[4.056407489],"iteration":443,"passed_time":0.6502414419,"remaining_time":0.8142663101},
{"learn":[4.05238936],"iteration":444,"passed_time":0.6511258135,"remaining_time":0.8120782618},
{"learn":[4.049685254],"iteration":445,"passed_time":0.6521486982,"remaining_time":0.8100681139},
{"learn":[4.045162016],"iteration":446,"passed_time":0.6530975167,"remaining_time":0.8079707533},
{"learn":[4.042955482],"iteration":447,"passed_time":0.6542394402,"remaining_time":0.8061164531},
{"learn":[4.041467663],"iteration":448,"passed_time":0.6551448512,"remaining_time":0.8039750847},
{"learn":[4.038920476],"iteration":449,"passed_time":0.6561244685,"remaining_time":0.801929906},
{"learn":[4.036694383],"iteration":450,"passed_time":0.6571332611,"remaining_time":0.7999249675},
{"learn":[4.034999007],"iteration":451,"passed_time":0.6580410008,"remaining_time":0.7978019214},
{"learn":[4.031928018],"iteration":452,"passed_time":0.6589117292,"remaining_time":0.7956395493},
{"learn":[4.028718143],"iteration":453,"passed_time":0.6598050509,"remaining_time":0.7935100392},
{"learn":[4.027401978],"iteration":454,"passed_time":0.6607204706,"remaining_time":0.7914124318},
{"learn":[4.025930598],"iteration":455,"passed_time":0.6616940015,"remaining_time":0.7893893352},
{"learn":[4.021074523],"iteration":456,"passed_time":0.6625582772,"remaining_time":0.7872410165},
{"learn":[4.020268486],"iteration":457,"passed_time":0.6635265403,"remaining_time":0.7852213643},
{"learn":[4.017986361],"iteration":458,"passed_time":0.6647366983,"remaining_time":0.7834914026},
{"learn":[4.014814804],"iteration":459,"passed_time":0.6656184508,"remaining_time":0.7813781814},
{"learn":[4.009704796],"iteration":460,"passed_time":0.6668323944,"remaining_time":0.7796586997},
{"learn":[4.008440457],"iteration":461,"passed_time":0.6678180917,"remaining_time":0.7776756133},
{"learn":[4.004854849],"iteration":462,"passed_time":0.6690098899,"remaining_time":0.7759358766},
{"learn":[4.000898028],"iteration":463,"passed_time":0.6699553528,"remaining_time":0.7739139421},
{"learn":[3.996617985],"iteration":464,"passed_time":0.6708560374,"remaining_time":0.7718451183},
{"learn":[3.995443319],"iteration":465,"passed_time":0.6717580046,"remaining_time":0.7697827778},
{"learn":[3.990771995],"iteration":466,"passed_time":0.672678115,"remaining_time":0.7677461141},
{"learn":[3.989249359],"iteration":467,"passed_time":0.6735927204,"remaining_time":0.7657079642},
{"learn":[3.986599538],"iteration":468,"passed_time":0.6745841486,"remaining_time":0.763761584},
{"learn":[3.985628919],"iteration":469,"passed_time":0.6755020782,"remaining_time":0.7617363861},
{"learn":[3.985086112],"iteration":470,"passed_time":0.6767314941,"remaining_time":0.7600657333},
{"learn":[3.98466839],"iteration":471,"passed_time":0.6778442291,"remaining_time":0.7582664257},
{"learn":[3.984233894],"iteration":472,"passed_time":0.6787091307,"remaining_time":0.756193894},
{"learn":[3.981855845],"iteration":473,"passed_time":0.6796760902,"remaining_time":0.754239712},
{"learn":[3.978684264],"iteration":474,"passed_time":0.6808396979,"remaining_time":0.7525070345},
{"learn":[3.974361269],"iteration":475,"passed_time":0.6817496104,"remaining_time":0.7504974703},
{"learn":[3.972074049],"iteration":476,"passed_time":0.6827388067,"remaining_time":0.7485794463},
{"learn":[3.97191982],"iteration":477,"passed_time":0.6835872858,"remaining_time":0.7465116385},
{"learn":[3.969616848],"iteration":478,"passed_time":0.6844443371,"remaining_time":0.7444582456},
{"learn":[3.968533527],"iteration":479,"passed_time":0.6852873737,"remaining_time":0.7423946549},
{"learn":[3.967568753],"iteration":480,"passed_time":0.6862172789,"remaining_time":0.7404298706},
{"learn":[3.966232553],"iteration":481,"passed_time":0.6871604415,"remaining_time":0.7384836281},
{"learn":[3.961522393],"iteration":482,"passed_time":0.6880675837,"remaining_time":0.736502983},
{"learn":[3.955829553],"iteration":483,"passed_time":0.6891678988,"remaining_time":0.7347327186},
{"learn":[3.954248095],"iteration":484,"passed_time":0.6901228808,"remaining_time":0.732810894},
{"learn":[3.951922606],"iteration":485,"passed_time":0.691350921,"remaining_time":0.7311818383},
{"learn":[3.94978202],"iteration":486,"passed_time":0.6923306892,"remaining_time":0.7292929026},
{"learn":[3.949518999],"iteration":487,"passed_time":0.6933746641,"remaining_time":0.7274750574},
{"learn":[3.945431216],"iteration":488,"passed_time":0.6944048407,"remaining_time":0.7256459583},
{"learn":[3.943249086],"iteration":489,"passed_time":0.6953862625,"remaining_time":0.7237693752},
{"learn":[3.941981548],"iteration":490,"passed_time":0.696337305,"remaining_time":0.7218649455},
{"learn":[3.936600517],"iteration":491,"passed_time":0.6973339041,"remaining_time":0.7200114294},
{"learn":[3.934476885],"iteration":492,"passed_time":0.6982098398,"remaining_time":0.7180372998},
{"learn":[3.93045798],"iteration":493,"passed_time":0.6991657727,"remaining_time":0.7161495567},
{"learn":[3.925977375],"iteration":494,"passed_time":0.7000164064,"remaining_time":0.7141581519},
{"learn":[3.92457993],"iteration":495,"passed_time":0.7010283669,"remaining_time":0.712335276},
{"learn":[3.919849146],"iteration":496,"passed_time":0.7019792036,"remaining_time":0.7104538016},
{"learn":[3.919681964],"iteration":497,"passed_time":0.7028284241,"remaining_time":0.7084736323},
{"learn":[3.917633027],"iteration":498,"passed_time":0.7037089826,"remaining_time":0.7065294595},
{"learn":[3.916616419],"iteration":499,"passed_time":0.7045246585,"remaining_time":0.7045246585},
{"learn":[3.912896166],"iteration":500,"passed_time":0.7054069669,"remaining_time":0.702590971},
{"learn":[3.912769674],"iteration":501,"passed_time":0.7063175254,"remaining_time":0.7006894973},
{"learn":[3.909373788],"iteration":502,"passed_time":0.7071680669,"remaining_time":0.6987326626},
{"learn":[3.906706036],"iteration":503,"passed_time":0.7081498696,"remaining_time":0.6969093954},
{"learn":[3.903895664],"iteration":504,"passed_time":0.708991676,"remaining_time":0.6949522369},
{"learn":[3.902982967],"iteration":505,"passed_time":0.7098911008,"remaining_time":0.6930557387},
{"learn":[3.900905528],"iteration":506,"passed_time":0.7107137935,"remaining_time":0.6910885606},
{"learn":[3.897463465],"iteration":507,"passed_time":0.7116469,"remaining_time":0.6892328244},
{"learn":[3.895918033],"iteration":508,"passed_time":0.7125235405,"remaining_time":0.6873262444},
{"learn":[3.893921936],"iteration":509,"passed_time":0.7133744342,"remaining_time":0.6853989662},
{"learn":[3.890237934],"iteration":510,"passed_time":0.7142404235,"remaining_time":0.6834903465},
{"learn":[3.887311613],"iteration":511,"passed_time":0.7151094411,"remaining_time":0.6815886861},
{"learn":[3.884869735],"iteration":512,"passed_time":0.7160106966,"remaining_time":0.6797216554},
{"learn":[3.882101231],"iteration":513,"passed_time":0.7168685163,"remaining_time":0.677817313},
{"learn":[3.88060368],"iteration":514,"passed_time":0.7177973767,"remaining_time":0.6759839373},
{"learn":[3.877726076],"iteration":515,"passed_time":0.7186661914,"remaining_time":0.6740977454},
{"learn":[3.874938145],"iteration":516,"passed_time":0.7195964479,"remaining_time":0.6722728904},
{"learn":[3.874340833],"iteration":517,"passed_time":0.7204441511,"remaining_time":0.6703746734},
{"learn":[3.873105224],"iteration":518,"passed_time":0.7212797762,"remaining_time":0.6684693109},
{"learn":[3.869800236],"iteration":519,"passed_time":0.722285973,"remaining_time":0.6667255135},
{"learn":[3.867932518],"iteration":520,"passed_time":0.7232608262,"remaining_time":0.6649557308},
{"learn":[3.866666962],"iteration":521,"passed_time":0.7240442547,"remaining_time":0.6630137045},
{"learn":[3.865527652],"iteration":522,"passed_time":0.7248863387,"remaining_time":0.6611296052},
{"learn":[3.861900081],"iteration":523,"passed_time":0.7257268349,"remaining_time":0.6592480409},
{"learn":[3.858502887],"iteration":524,"passed_time":0.7266646371,"remaining_time":0.6574584812},
{"learn":[3.858335097],"iteration":525,"passed_time":0.7274982215,"remaining_time":0.6555782453},
{"learn":[3.855719306],"iteration":526,"passed_time":0.7283103906,"remaining_time":0.6536827604},
{"learn":[3.855137428],"iteration":527,"passed_time":0.7292012478,"remaining_time":0.6518617215},
{"learn":[3.851985706],"iteration":528,"passed_time":0.7300832878,"remaining_time":0.6500363489},
{"learn":[3.851051809],"iteration":529,"passed_time":0.7310510658,"remaining_time":0.6482905678},
{"learn":[3.850679146],"iteration":530,"passed_time":0.7319838119,"remaining_time":0.6465167755},
{"learn":[3.848179484],"iteration":531,"passed_time":0.7328576615,"remaining_time":0.6446943338},
{"learn":[3.844551071],"iteration":532,"passed_time":0.7337671995,"remaining_time":0.6429067207},
{"learn":[3.841604794],"iteration":533,"passed_time":0.7346132732,"remaining_time":0.6410670137},
{"learn":[3.83969656],"iteration":534,"passed_time":0.7354635618,"remaining_time":0.6392346846},
{"learn":[3.836811463],"iteration":535,"passed_time":0.736428984,"remaining_time":0.6375056877},
{"learn":[3.834182551],"iteration":536,"passed_time":0.7374085167,"remaining_time":0.6357917007},
{"learn":[3.828012842],"iteration":537,"passed_time":0.7382177808,"remaining_time":0.6339342281},
{"learn":[3.826636176],"iteration":538,"passed_time":0.7391612134,"remaining_time":0.6321953978},
{"learn":[3.826189798],"iteration":539,"passed_time":0.7399557073,"remaining_time":0.6303326396},
{"learn":[3.824104738],"iteration":540,"passed_time":0.7408939288,"remaining_time":0.6285957732},
{"learn":[3.82300218],"iteration":541,"passed_time":0.7417973866,"remaining_time":0.626832478},
{"learn":[3.817146402],"iteration":542,"passed_time":0.7426880567,"remaining_time":0.6250615874},
{"learn":[3.814638044],"iteration":543,"passed_time":0.7435774475,"remaining_time":0.6232928604},
{"learn":[3.812979573],"iteration":544,"passed_time":0.7446737207,"remaining_time":0.6217000788},
{"learn":[3.811938825],"iteration":545,"passed_time":0.7455720053,"remaining_time":0.6199444879},
{"learn":[3.811479418],"iteration":546,"passed_time":0.7464333464,"remaining_time":0.6181614368},
{"learn":[3.80742981],"iteration":547,"passed_time":0.7473587172,"remaining_time":0.6164345623},
{"learn":[3.805097043],"iteration":548,"passed_time":0.748378961,"remaining_time":0.6147885454},
{"learn":[3.801577232],"iteration":549,"passed_time":0.7493553362,"remaining_time":0.6131089114},
{"learn":[3.799762083],"iteration":550,"passed_time":0.7502357485,"remaining_time":0.6113536317},
{"learn":[3.796393455],"iteration":551,"passed_time":0.7512169406,"remaining_time":0.6096833141},
{"learn":[3.793486459],"iteration":552,"passed_time":0.7522654525,"remaining_time":0.6080699046},
{"learn":[3.792006091],"iteration":553,"passed_time":0.7532917064,"remaining_time":0.6064406156},
{"learn":[3.78932128],"iteration":554,"passed_time":0.7546833922,"remaining_time":0.6051065037},
{"learn":[3.787581812],"iteration":555,"passed_time":0.7559837831,"remaining_time":0.60369928},
{"learn":[3.785308865],"iteration":556,"passed_time":0.7578607931,"remaining_time":0.6027510437},
{"learn":[3.78465475],"iteration":557,"passed_time":0.7592206379,"remaining_time":0.6013898243},
{"learn":[3.780498869],"iteration":558,"passed_time":0.760603387,"remaining_time":0.6000466792},
{"learn":[3.778734909],"iteration":559,"passed_time":0.7615298358,"remaining_time":0.598344871},
{"learn":[3.778652349],"iteration":560,"passed_time":0.7623496206,"remaining_time":0.5965623591},
{"learn":[3.777928006],"iteration":561,"passed_time":0.763246798,"remaining_time":0.5948435899},
{"learn":[3.776131406],"iteration":562,"passed_time":0.7641375981,"remaining_time":0.5931227893},
{"learn":[3.772925617],"iteration":563,"passed_time":0.7651628144,"remaining_time":0.5915088423},
{"learn":[3.7727745],"iteration":564,"passed_time":0.7660273259,"remaining_time":0.5897732509},
{"learn":[3.771763073],"iteration":565,"passed_time":0.7669136041,"remaining_time":0.5880574279},
{"learn":[3.768738162],"iteration":566,"passed_time":0.7679023144,"remaining_time":0.5864227551},
{"learn":[3.767220794],"iteration":567,"passed_time":0.7690604021,"remaining_time":0.584919179},
{"learn":[3.766691102],"iteration":568,"passed_time":0.7701318212,"remaining_time":0.5833511686},
{"learn":[3.766259335],"iteration":569,"passed_time":0.7710079503,"remaining_time":0.5816375765},
{"learn":[3.76116362],"iteration":570,"passed_time":0.7719983817,"remaining_time":0.5800127947},
{"learn":[3.758633056],"iteration":571,"passed_time":0.7730067655,"remaining_time":0.5784036637},
{"learn":[3.754603809],"iteration":572,"passed_time":0.773921628,"remaining_time":0.5767269374},
{"learn":[3.754070549],"iteration":573,"passed_time":0.7747712764,"remaining_time":0.5750044665},
{"learn":[3.750534319],"iteration":574,"passed_time":0.7757457542,"remaining_time":0.5733772966},
{"learn":[3.746491516],"iteration":575,"passed_time":0.7766865377,"remaining_time":0.5717275903},
{"learn":[3.744210544],"iteration":576,"passed_time":0.7775531033,"remaining_time":0.5700259319},
{"learn":[3.742929991],"iteration":577,"passed_time":0.7784441097,"remaining_time":0.5683450075},
{"learn":[3.740402992],"iteration":578,"passed_time":0.7793076103,"remaining_time":0.5666468116},
{"learn":[3.739644243],"iteration":579,"passed_time":0.7801265425,"remaining_time":0.5649192204},
{"learn":[3.737529404],"iteration":580,"passed_time":0.7822843821,"remaining_time":0.5641603375},
{"learn":[3.737196923],"iteration":581,"passed_time":0.7832220897,"remaining_time":0.5625203325},
{"learn":[3.733954464],"iteration":582,"passed_time":0.784120556,"remaining_time":0.5608546687},
{"learn":[3.731608623],"iteration":583,"passed_time":0.7850183247,"remaining_time":0.5591911354},
{"learn":[3.729843952],"iteration":584,"passed_time":0.7863417523,"remaining_time":0.5578321833},
{"learn":[3.727223798],"iteration":585,"passed_time":0.7872931207,"remaining_time":0.5562104983},
{"learn":[3.725351667],"iteration":586,"passed_time":0.788282094,"remaining_time":0.5546175551},
{"learn":[3.725026912],"iteration":587,"passed_time":0.7890850163,"remaining_time":0.5528963039},
{"learn":[3.721974565],"iteration":588,"passed_time":0.7900280305,"remaining_time":0.5512759262},
{"learn":[3.720269493],"iteration":589,"passed_time":0.790869557,"remaining_time":0.5495873192},
{"learn":[3.718907466],"iteration":590,"passed_time":0.7918241342,"remaining_time":0.5479798154},
{"learn":[3.715602912],"iteration":591,"passed_time":0.7927690146,"remaining_time":0.5463678344},
{"learn":[3.714463059],"iteration":592,"passed_time":0.793600782,"remaining_time":0.5446804693},
{"learn":[3.710802077],"iteration":593,"passed_time":0.795109351,"remaining_time":0.54345858},
{"learn":[3.708032435],"iteration":594,"passed_time":0.7961552,"remaining_time":0.5419207664},
{"learn":[3.703788939],"iteration":595,"passed_time":0.7971509593,"remaining_time":0.5403506502},
{"learn":[3.702500944],"iteration":596,"passed_time":0.7980420007,"remaining_time":0.5387117693},
{"learn":[3.698196925],"iteration":597,"passed_time":0.7990412943,"remaining_time":0.537148161},
{"learn":[3.69658891],"iteration":598,"passed_time":0.7999852479,"remaining_time":0.5355493896},
{"learn":[3.696124066],"iteration":599,"passed_time":0.8010582793,"remaining_time":0.5340388529},
{"learn":[3.693537052],"iteration":600,"passed_time":0.8019552262,"remaining_time":0.5324128706},
{"learn":[3.691343275],"iteration":601,"passed_time":0.8029297635,"remaining_time":0.5308406078},
{"learn":[3.690973831],"iteration":602,"passed_time":0.8038016904,"remaining_time":0.5292027713},
{"learn":[3.686151073],"iteration":603,"passed_time":0.8047840743,"remaining_time":0.5276398898},
{"learn":[3.683921982],"iteration":604,"passed_time":0.8056748086,"remaining_time":0.5260190899},
{"learn":[3.679975271],"iteration":605,"passed_time":0.8065860126,"remaining_time":0.5244140082},
{"learn":[3.674047638],"iteration":606,"passed_time":0.8074914641,"remaining_time":0.5228074883},
{"learn":[3.673151794],"iteration":607,"passed_time":0.8086531415,"remaining_time":0.5213684728},
{"learn":[3.670953108],"iteration":608,"passed_time":0.8096174777,"remaining_time":0.5198036679},
{"learn":[3.6703947],"iteration":609,"passed_time":0.8105369976,"remaining_time":0.5182121788},
{"learn":[3.668433805],"iteration":610,"passed_time":0.8116488978,"remaining_time":0.5167453703},
{"learn":[3.668304956],"iteration":611,"passed_time":0.8125201912,"remaining_time":0.51512718},
{"learn":[3.667880012],"iteration":612,"passed_time":0.813398972,"remaining_time":0.5135161536},
{"learn":[3.667282264],"iteration":613,"passed_time":0.8143574019,"remaining_time":0.5119575849},
{"learn":[3.664611483],"iteration":614,"passed_time":0.8153293685,"remaining_time":0.5104094421},
{"learn":[3.662543394],"iteration":615,"passed_time":0.8162338294,"remaining_time":0.5088210885},
{"learn":[3.659041959],"iteration":616,"passed_time":0.817077667,"remaining_time":0.50719732},
{"learn":[3.656868545],"iteration":617,"passed_time":0.8180209542,"remaining_time":0.5056375478},
{"learn":[3.654785614],"iteration":618,"passed_time":0.8189697956,"remaining_time":0.504083186},
{"learn":[3.654566096],"iteration":619,"passed_time":0.8199527018,"remaining_time":0.5025516559},
{"learn":[3.651007045],"iteration":620,"passed_time":0.8212421113,"remaining_time":0.5012089536},
{"learn":[3.648921786],"iteration":621,"passed_time":0.8221323009,"remaining_time":0.4996238099},
{"learn":[3.647655706],"iteration":622,"passed_time":0.8229790273,"remaining_time":0.498014596},
{"learn":[3.647241144],"iteration":623,"passed_time":0.8238261371,"remaining_time":0.4964080569},
{"learn":[3.644195689],"iteration":624,"passed_time":0.8252043363,"remaining_time":0.4951226018},
{"learn":[3.642632246],"iteration":625,"passed_time":0.8261149815,"remaining_time":0.4935575129},
{"learn":[3.642523322],"iteration":626,"passed_time":0.8267606458,"remaining_time":0.4918368754},
{"learn":[3.641494659],"iteration":627,"passed_time":0.8276547581,"remaining_time":0.4902668312},
{"learn":[3.63976496],"iteration":628,"passed_time":0.8285087214,"remaining_time":0.4886752554},
{"learn":[3.637945652],"iteration":629,"passed_time":0.829443411,"remaining_time":0.4871334319},
{"learn":[3.636233667],"iteration":630,"passed_time":0.8303995269,"remaining_time":0.4856060625},
{"learn":[3.635304404],"iteration":631,"passed_time":0.8312784748,"remaining_time":0.4840355676},
{"learn":[3.632234951],"iteration":632,"passed_time":0.8322525825,"remaining_time":0.4825224293},
{"learn":[3.631630987],"iteration":633,"passed_time":0.8334359885,"remaining_time":0.4811318167},
{"learn":[3.630301009],"iteration":634,"passed_time":0.834723552,"remaining_time":0.4798017267},
{"learn":[3.629077964],"iteration":635,"passed_time":0.8357623624,"remaining_time":0.4783294024},
{"learn":[3.628004522],"iteration":636,"passed_time":0.8366196612,"remaining_time":0.4767550031},
{"learn":[3.625062876],"iteration":637,"passed_time":0.837692343,"remaining_time":0.4753050598},
{"learn":[3.624917986],"iteration":638,"passed_time":0.8386863487,"remaining_time":0.4738118496},
{"learn":[3.622887087],"iteration":639,"passed_time":0.8396238671,"remaining_time":0.4722884252},
{"learn":[3.621220865],"iteration":640,"passed_time":0.840603599,"remaining_time":0.4707904712},
{"learn":[3.621143844],"iteration":641,"passed_time":0.8413972119,"remaining_time":0.4691903456},
{"learn":[3.620822821],"iteration":642,"passed_time":0.8421896501,"remaining_time":0.4675920763},
{"learn":[3.619202826],"iteration":643,"passed_time":0.8430561378,"remaining_time":0.4660372439},
{"learn":[3.618204882],"iteration":644,"passed_time":0.8440023463,"remaining_time":0.4645284231},
{"learn":[3.614259666],"iteration":645,"passed_time":0.8448277903,"remaining_time":0.4629551668},
{"learn":[3.613415661],"iteration":646,"passed_time":0.8457624999,"remaining_time":0.4614438369},
{"learn":[3.611096773],"iteration":647,"passed_time":0.847114859,"remaining_time":0.460161158},
{"learn":[3.610820695],"iteration":648,"passed_time":0.8481098332,"remaining_time":0.4586849791},
{"learn":[3.609290065],"iteration":649,"passed_time":0.8489660977,"remaining_time":0.4571355911},
{"learn":[3.60897947],"iteration":650,"passed_time":0.8498699131,"remaining_time":0.4556138244},
{"learn":[3.606570702],"iteration":651,"passed_time":0.8509659363,"remaining_time":0.4541965427},
{"learn":[3.606292637],"iteration":652,"passed_time":0.8519096724,"remaining_time":0.4526993205},
{"learn":[3.602753838],"iteration":653,"passed_time":0.8528744587,"remaining_time":0.4512149277},
{"learn":[3.599755869],"iteration":654,"passed_time":0.8537365757,"remaining_time":0.4496780437},
{"learn":[3.599509575],"iteration":655,"passed_time":0.8547128217,"remaining_time":0.448203065},
{"learn":[3.595337722],"iteration":656,"passed_time":0.8556648189,"remaining_time":0.4467169451},
{"learn":[3.595168561],"iteration":657,"passed_time":0.8566999921,"remaining_time":0.4452756798},
{"learn":[3.59290559],"iteration":658,"passed_time":0.8576584979,"remaining_time":0.4437959754},
{"learn":[3.592015928],"iteration":659,"passed_time":0.8585164902,"remaining_time":0.4422660707},
{"learn":[3.590680403],"iteration":660,"passed_time":0.8595094857,"remaining_time":0.4408074367},
{"learn":[3.590361532],"iteration":661,"passed_time":0.8617317918,"remaining_time":0.4399778635},
{"learn":[3.589069739],"iteration":662,"passed_time":0.8626615774,"remaining_time":0.4384871064},
{"learn":[3.585010186],"iteration":663,"passed_time":0.8634846918,"remaining_time":0.4369440609},
{"learn":[3.582997552],"iteration":664,"passed_time":0.8645237906,"remaining_time":0.4355119847},
{"learn":[3.582119256],"iteration":665,"passed_time":0.8655217536,"remaining_time":0.434060459},
{"learn":[3.579019356],"iteration":666,"passed_time":0.8663977694,"remaining_time":0.4325494111},
{"learn":[3.57719559],"iteration":667,"passed_time":0.8672611558,"remaining_time":0.4310339876},
{"learn":[3.574050046],"iteration":668,"passed_time":0.8681856814,"remaining_time":0.4295507632},
{"learn":[3.572204518],"iteration":669,"passed_time":0.8691196914,"remaining_time":0.4280738779},
{"learn":[3.569508025],"iteration":670,"passed_time":0.8700760564,"remaining_time":0.4266095716},
{"learn":[3.566268704],"iteration":671,"passed_time":0.8710873018,"remaining_time":0.425173564},
{"learn":[3.562564052],"iteration":672,"passed_time":0.8720160406,"remaining_time":0.42369873},
{"learn":[3.561173586],"iteration":673,"passed_time":0.8729799197,"remaining_time":0.4222425131},
{"learn":[3.559551904],"iteration":674,"passed_time":0.8743517734,"remaining_time":0.4209841872},
{"learn":[3.558593054],"iteration":675,"passed_time":0.875303964,"remaining_time":0.4195243851},
{"learn":[3.555647008],"iteration":676,"passed_time":0.8762028008,"remaining_time":0.4180406273},
{"learn":[3.553100059],"iteration":677,"passed_time":0.8773723155,"remaining_time":0.4166871469},
{"learn":[3.55085578],"iteration":678,"passed_time":0.8784497931,"remaining_time":0.4152906975},
{"learn":[3.550737965],"iteration":679,"passed_time":0.8793201943,"remaining_time":0.4137977385},
{"learn":[3.549408772],"iteration":680,"passed_time":0.8802552719,"remaining_time":0.4123369042},
{"learn":[3.547390589],"iteration":681,"passed_time":0.8811825129,"remaining_time":0.4108739576},
{"learn":[3.54723575],"iteration":682,"passed_time":0.8820037463,"remaining_time":0.4093633786},
{"learn":[3.543988891],"iteration":683,"passed_time":0.8829364165,"remaining_time":0.4079062977},
{"learn":[3.543868508],"iteration":684,"passed_time":0.8838179744,"remaining_time":0.4064272437},
{"learn":[3.542752124],"iteration":685,"passed_time":0.8847759213,"remaining_time":0.4049848969},
{"learn":[3.541334315],"iteration":686,"passed_time":0.8856912631,"remaining_time":0.4035245493},
{"learn":[3.540208266],"iteration":687,"passed_time":0.8869061493,"remaining_time":0.4022016258},
{"learn":[3.537730983],"iteration":688,"passed_time":0.8880398861,"remaining_time":0.4008423869},
{"learn":[3.53419867],"iteration":689,"passed_time":0.88898889,"remaining_time":0.3994008057},
{"learn":[3.532628335],"iteration":690,"passed_time":0.8902042251,"remaining_time":0.3980797475},
{"learn":[3.532204987],"iteration":691,"passed_time":0.8913088446,"remaining_time":0.396709717},
{"learn":[3.530618147],"iteration":692,"passed_time":0.8921683979,"remaining_time":0.3952318877},
{"learn":[3.528909306],"iteration":693,"passed_time":0.8930813143,"remaining_time":0.3937793691},
{"learn":[3.526700678],"iteration":694,"passed_time":0.8939587336,"remaining_time":0.3923128255},
{"learn":[3.526439574],"iteration":695,"passed_time":0.8948802671,"remaining_time":0.3908672431},
{"learn":[3.525784216],"iteration":696,"passed_time":0.8957393329,"remaining_time":0.3893960084},
{"learn":[3.524112693],"iteration":697,"passed_time":0.8966692843,"remaining_time":0.3879571975},
{"learn":[3.522813541],"iteration":698,"passed_time":0.8976094315,"remaining_time":0.386524233},
{"learn":[3.519148203],"iteration":699,"passed_time":0.8988009475,"remaining_time":0.3852004061},
{"learn":[3.517236747],"iteration":700,"passed_time":0.9001241776,"remaining_time":0.3839331371},
{"learn":[3.515603888],"iteration":701,"passed_time":0.9011036894,"remaining_time":0.3825197998},
{"learn":[3.51263524],"iteration":702,"passed_time":0.9020151723,"remaining_time":0.3810789561},
{"learn":[3.51123442],"iteration":703,"passed_time":0.9032799748,"remaining_time":0.3797881712},
{"learn":[3.50828027],"iteration":704,"passed_time":0.904257483,"remaining_time":0.3783772447},
{"learn":[3.508265537],"iteration":705,"passed_time":0.9047948038,"remaining_time":0.3767842384},
{"learn":[3.506774876],"iteration":706,"passed_time":0.9056498098,"remaining_time":0.3753258759},
{"learn":[3.50552068],"iteration":707,"passed_time":0.9065312043,"remaining_time":0.3738801012},
{"learn":[3.501973993],"iteration":708,"passed_time":0.9074223916,"remaining_time":0.3724399379},
{"learn":[3.498880354],"iteration":709,"passed_time":0.9083585027,"remaining_time":0.3710196701},
{"learn":[3.497370959],"iteration":710,"passed_time":0.9092839243,"remaining_time":0.3695964193},
{"learn":[3.496050455],"iteration":711,"passed_time":0.9102003987,"remaining_time":0.3681709478},
{"learn":[3.495630067],"iteration":712,"passed_time":0.9110099411,"remaining_time":0.3667038613},
{"learn":[3.49550669],"iteration":713,"passed_time":0.9122376222,"remaining_time":0.3654061064},
{"learn":[3.493652375],"iteration":714,"passed_time":0.9136029878,"remaining_time":0.3641634287},
{"learn":[3.491915684],"iteration":715,"passed_time":0.914570247,"remaining_time":0.3627625002},
{"learn":[3.490303956],"iteration":716,"passed_time":0.9154941842,"remaining_time":0.3613456822},
{"learn":[3.488363853],"iteration":717,"passed_time":0.9165838552,"remaining_time":0.3599953303},
{"learn":[3.485483936],"iteration":718,"passed_time":0.9175332938,"remaining_time":0.3585908979},
{"learn":[3.483763466],"iteration":719,"passed_time":0.9185972709,"remaining_time":0.357232272},
{"learn":[3.481642352],"iteration":720,"passed_time":0.9195231472,"remaining_time":0.3558210237},
{"learn":[3.479826119],"iteration":721,"passed_time":0.9204670707,"remaining_time":0.3544180688},
{"learn":[3.478588728],"iteration":722,"passed_time":0.9213360546,"remaining_time":0.3529876724},
{"learn":[3.475390887],"iteration":723,"passed_time":0.9222448962,"remaining_time":0.3515740212},
{"learn":[3.472636852],"iteration":724,"passed_time":0.9232083536,"remaining_time":0.3501824789},
{"learn":[3.47061883],"iteration":725,"passed_time":0.9241840478,"remaining_time":0.3487967343},
{"learn":[3.46953149],"iteration":726,"passed_time":0.9256498599,"remaining_time":0.3475961647},
{"learn":[3.467217162],"iteration":727,"passed_time":0.9266435801,"remaining_time":0.3462184805},
{"learn":[3.465686216],"iteration":728,"passed_time":0.9275822491,"remaining_time":0.3448213848},
{"learn":[3.462631216],"iteration":729,"passed_time":0.9286336702,"remaining_time":0.3434672479},
{"learn":[3.461451053],"iteration":730,"passed_time":0.929726543,"remaining_time":0.342129193},
{"learn":[3.458950469],"iteration":731,"passed_time":0.930717407,"remaining_time":0.3407544605},
{"learn":[3.458072145],"iteration":732,"passed_time":0.9315931319,"remaining_time":0.3393388352},
{"learn":[3.454364268],"iteration":733,"passed_time":0.93268548,"remaining_time":0.3380031848},
{"learn":[3.453243406],"iteration":734,"passed_time":0.9335781162,"remaining_time":0.3365961916},
{"learn":[3.453017963],"iteration":735,"passed_time":0.9345542021,"remaining_time":0.335220529},
{"learn":[3.45201581],"iteration":736,"passed_time":0.9355387639,"remaining_time":0.3338489755},
{"learn":[3.449510107],"iteration":737,"passed_time":0.9364181927,"remaining_time":0.332441147},
{"learn":[3.447189189],"iteration":738,"passed_time":0.9375436229,"remaining_time":0.3311216314},
{"learn":[3.446423605],"iteration":739,"passed_time":0.9389850417,"remaining_time":0.3299136633},
{"learn":[3.445531987],"iteration":740,"passed_time":0.9399947477,"remaining_time":0.3285541696},
{"learn":[3.445328199],"iteration":741,"passed_time":0.9409115476,"remaining_time":0.3271633144},
{"learn":[3.443327544],"iteration":742,"passed_time":0.9418702863,"remaining_time":0.3257882417},
{"learn":[3.441475798],"iteration":743,"passed_time":0.9429428535,"remaining_time":0.324453455},
{"learn":[3.439046501],"iteration":744,"passed_time":0.9438374421,"remaining_time":0.3230584533},
{"learn":[3.435899469],"iteration":745,"passed_time":0.9447503273,"remaining_time":0.321671023},
{"learn":[3.433988352],"iteration":746,"passed_time":0.9457030121,"remaining_time":0.3202983428},
{"learn":[3.433413263],"iteration":747,"passed_time":0.9465573422,"remaining_time":0.31889365},
{"learn":[3.429944699],"iteration":748,"passed_time":0.9475193726,"remaining_time":0.3175265187},
{"learn":[3.429291634],"iteration":749,"passed_time":0.9484180552,"remaining_time":0.3161393517},
{"learn":[3.429175603],"iteration":750,"passed_time":0.9493336974,"remaining_time":0.3147591087},
{"learn":[3.428780323],"iteration":751,"passed_time":0.9501604682,"remaining_time":0.3133507927},
{"learn":[3.423893341],"iteration":752,"passed_time":0.9512037318,"remaining_time":0.3120150355},
{"learn":[3.421024316],"iteration":753,"passed_time":0.9527894041,"remaining_time":0.3108570204},
{"learn":[3.420969872],"iteration":754,"passed_time":0.9537438434,"remaining_time":0.3094930353},
{"learn":[3.419544785],"iteration":755,"passed_time":0.9545664795,"remaining_time":0.3080875939},
{"learn":[3.417057977],"iteration":756,"passed_time":0.9556271965,"remaining_time":0.3067601173},
{"learn":[3.415160245],"iteration":757,"passed_time":0.9566140608,"remaining_time":0.3054097661},
{"learn":[3.412854597],"iteration":758,"passed_time":0.9575575609,"remaining_time":0.3040466037},
{"learn":[3.410926347],"iteration":759,"passed_time":0.9583770907,"remaining_time":0.3026453971},
{"learn":[3.408963843],"iteration":760,"passed_time":0.9592562078,"remaining_time":0.3012644332},
{"learn":[3.407629634],"iteration":761,"passed_time":0.9600599918,"remaining_time":0.2998612573},
{"learn":[3.404384724],"iteration":762,"passed_time":0.9610157601,"remaining_time":0.2985068613},
{"learn":[3.403041656],"iteration":763,"passed_time":0.9620689719,"remaining_time":0.2971836091},
{"learn":[3.401101731],"iteration":764,"passed_time":0.962903253,"remaining_time":0.2957938098},
{"learn":[3.400890668],"iteration":765,"passed_time":0.9639596953,"remaining_time":0.2944733273},
{"learn":[3.399289941],"iteration":766,"passed_time":0.9653905729,"remaining_time":0.2932672796},
{"learn":[3.399202366],"iteration":767,"passed_time":0.9662521798,"remaining_time":0.2918886793},
{"learn":[3.397447845],"iteration":768,"passed_time":0.9672539317,"remaining_time":0.2905535218},
{"learn":[3.394655341],"iteration":769,"passed_time":0.9682572826,"remaining_time":0.2892197078},
{"learn":[3.393228229],"iteration":770,"passed_time":0.9691990042,"remaining_time":0.2878684461},
{"learn":[3.389691197],"iteration":771,"passed_time":0.9701260544,"remaining_time":0.2865139124},
{"learn":[3.389626772],"iteration":772,"passed_time":0.9710143645,"remaining_time":0.2851491083},
{"learn":[3.388480222],"iteration":773,"passed_time":0.9718374186,"remaining_time":0.2837664814},
{"learn":[3.388215066],"iteration":774,"passed_time":0.9726713976,"remaining_time":0.2823884703},
{"learn":[3.386324358],"iteration":775,"passed_time":0.9735893781,"remaining_time":0.2810361091},
{"learn":[3.383913061],"iteration":776,"passed_time":0.9744745953,"remaining_time":0.279675463},
{"learn":[3.382839768],"iteration":777,"passed_time":0.9753848075,"remaining_time":0.2783231713},
{"learn":[3.381961844],"iteration":778,"passed_time":0.976203062,"remaining_time":0.2769459265},
{"learn":[3.381521703],"iteration":779,"passed_time":0.9774295429,"remaining_time":0.2756852557},
{"learn":[3.380918963],"iteration":780,"passed_time":0.9784706949,"remaining_time":0.2743727045},
{"learn":[3.377139006],"iteration":781,"passed_time":0.9794271404,"remaining_time":0.2730372335},
{"learn":[3.376004372],"iteration":782,"passed_time":0.9803677735,"remaining_time":0.2716983485},
{"learn":[3.373826468],"iteration":783,"passed_time":0.981475033,"remaining_time":0.2704063866},
{"learn":[3.373546786],"iteration":784,"passed_time":0.9824574707,"remaining_time":0.2690807085},
{"learn":[3.372109181],"iteration":785,"passed_time":0.9833279015,"remaining_time":0.2677254083},
{"learn":[3.370764924],"iteration":786,"passed_time":0.984261446,"remaining_time":0.2663884218},
{"learn":[3.367833107],"iteration":787,"passed_time":0.9852684528,"remaining_time":0.2650722234},
{"learn":[3.36450404],"iteration":788,"passed_time":0.9861093391,"remaining_time":0.2637123835},
{"learn":[3.361794558],"iteration":789,"passed_time":0.987027658,"remaining_time":0.2623744407},
{"learn":[3.356880529],"iteration":790,"passed_time":0.9880125853,"remaining_time":0.2610551584},
{"learn":[3.353843509],"iteration":791,"passed_time":0.9888459713,"remaining_time":0.2596969218},
{"learn":[3.353640253],"iteration":792,"passed_time":0.9900167842,"remaining_time":0.2584280887},
{"learn":[3.353055088],"iteration":793,"passed_time":0.9914283722,"remaining_time":0.2572219706},
{"learn":[3.351415617],"iteration":794,"passed_time":0.9923885032,"remaining_time":0.2558989222},
{"learn":[3.349169061],"iteration":795,"passed_time":0.993324749,"remaining_time":0.2545706643},
{"learn":[3.346211014],"iteration":796,"passed_time":0.9947303373,"remaining_time":0.2533629341},
{"learn":[3.344560452],"iteration":797,"passed_time":0.9958608187,"remaining_time":0.2520850694},
{"learn":[3.344445461],"iteration":798,"passed_time":0.9966633867,"remaining_time":0.2507250823},
{"learn":[3.342608898],"iteration":799,"passed_time":0.9975472437,"remaining_time":0.2493868109},
{"learn":[3.339572899],"iteration":800,"passed_time":0.9984160701,"remaining_time":0.24804594},
{"learn":[3.339309302],"iteration":801,"passed_time":0.999314413,"remaining_time":0.2467135334},
{"learn":[3.33698088],"iteration":802,"passed_time":1.000187108,"remaining_time":0.2453759156},
{"learn":[3.334746342],"iteration":803,"passed_time":1.001080655,"remaining_time":0.2440445378},
{"learn":[3.332048511],"iteration":804,"passed_time":1.00190502,"remaining_time":0.2426974893},
{"learn":[3.331932544],"iteration":805,"passed_time":1.002757734,"remaining_time":0.2413585612},
{"learn":[3.330541133],"iteration":806,"passed_time":1.005933343,"remaining_time":0.2405763757},
{"learn":[3.329124989],"iteration":807,"passed_time":1.007106726,"remaining_time":0.2393124894},
{"learn":[3.32583918],"iteration":808,"passed_time":1.008071813,"remaining_time":0.2379996493},
{"learn":[3.325287299],"iteration":809,"passed_time":1.009143889,"remaining_time":0.236712764},
{"learn":[3.322745162],"iteration":810,"passed_time":1.010166304,"remaining_time":0.2354148353},
{"learn":[3.319733662],"iteration":811,"passed_time":1.011061132,"remaining_time":0.2340880453},
{"learn":[3.318080007],"iteration":812,"passed_time":1.012105725,"remaining_time":0.2327967658},
{"learn":[3.317179538],"iteration":813,"passed_time":1.012983431,"remaining_time":0.2314679585},
{"learn":[3.315685949],"iteration":814,"passed_time":1.013903689,"remaining_time":0.2301499172},
{"learn":[3.314944576],"iteration":815,"passed_time":1.014854653,"remaining_time":0.2288397747},
{"learn":[3.312369052],"iteration":816,"passed_time":1.015995323,"remaining_time":0.2275730039},
{"learn":[3.312321621],"iteration":817,"passed_time":1.016751972,"remaining_time":0.226221099},
{"learn":[3.309465776],"iteration":818,"passed_time":1.018100045,"remaining_time":0.2250013531},
{"learn":[3.308307377],"iteration":819,"passed_time":1.019048027,"remaining_time":0.2236934693},
{"learn":[3.308076804],"iteration":820,"passed_time":1.019895643,"remaining_time":0.2223645798},
{"learn":[3.305643326],"iteration":821,"passed_time":1.020808276,"remaining_time":0.2210509405},
{"learn":[3.304154814],"iteration":822,"passed_time":1.021938646,"remaining_time":0.2197851036},
{"learn":[3.303076321],"iteration":823,"passed_time":1.022885854,"remaining_time":0.2184804737},
{"learn":[3.301746372],"iteration":824,"passed_time":1.023737219,"remaining_time":0.2171563799},
{"learn":[3.301345455],"iteration":825,"passed_time":1.024607541,"remaining_time":0.2158374239},
{"learn":[3.299181039],"iteration":826,"passed_time":1.025502373,"remaining_time":0.2145246801},
{"learn":[3.297989357],"iteration":827,"passed_time":1.026480759,"remaining_time":0.2132303026},
{"learn":[3.294775182],"iteration":828,"passed_time":1.027361437,"remaining_time":0.2119165329},
{"learn":[3.293840636],"iteration":829,"passed_time":1.028252375,"remaining_time":0.2106059082},
{"learn":[3.289279397],"iteration":830,"passed_time":1.029127072,"remaining_time":0.2092929905},
{"learn":[3.286204979],"iteration":831,"passed_time":1.031220663,"remaining_time":0.2082272493},
{"learn":[3.284833593],"iteration":832,"passed_time":1.032604827,"remaining_time":0.2070168141},
{"learn":[3.283519914],"iteration":833,"passed_time":1.033523571,"remaining_time":0.2057133247},
{"learn":[3.282853026],"iteration":834,"passed_time":1.034439728,"remaining_time":0.2044102457},
{"learn":[3.281944673],"iteration":835,"passed_time":1.035440516,"remaining_time":0.2031246945},
{"learn":[3.279764865],"iteration":836,"passed_time":1.0364608,"remaining_time":0.2018436206},
{"learn":[3.277468839],"iteration":837,"passed_time":1.037387908,"remaining_time":0.2005451565},
{"learn":[3.277124974],"iteration":838,"passed_time":1.038309718,"remaining_time":0.199246561},
{"learn":[3.275636037],"iteration":839,"passed_time":1.039168359,"remaining_time":0.1979368303},
{"learn":[3.274413635],"iteration":840,"passed_time":1.040054738,"remaining_time":0.1966334167},
{"learn":[3.272636087],"iteration":841,"passed_time":1.041119821,"remaining_time":0.195364527},
{"learn":[3.269644466],"iteration":842,"passed_time":1.042114234,"remaining_time":0.1940829594},
{"learn":[3.26852083],"iteration":843,"passed_time":1.043044086,"remaining_time":0.1927901392},
{"learn":[3.267820927],"iteration":844,"passed_time":1.044367606,"remaining_time":0.1915703892},
{"learn":[3.267331099],"iteration":845,"passed_time":1.045513423,"remaining_time":0.1903180463},
{"learn":[3.267231014],"iteration":846,"passed_time":1.04635126,"remaining_time":0.1890103221},
{"learn":[3.267158695],"iteration":847,"passed_time":1.047221507,"remaining_time":0.1877095154},
{"learn":[3.264718705],"iteration":848,"passed_time":1.048412954,"remaining_time":0.1864668505},
{"learn":[3.261678512],"iteration":849,"passed_time":1.049321289,"remaining_time":0.1851743452},
{"learn":[3.261368381],"iteration":850,"passed_time":1.050292147,"remaining_time":0.1838936896},
{"learn":[3.260128799],"iteration":851,"passed_time":1.051153413,"remaining_time":0.1825947243},
{"learn":[3.258972952],"iteration":852,"passed_time":1.052140587,"remaining_time":0.1813184834},
{"learn":[3.258724846],"iteration":853,"passed_time":1.053086681,"remaining_time":0.1800358963},
{"learn":[3.25686724],"iteration":854,"passed_time":1.054190516,"remaining_time":0.1787808478},
{"learn":[3.255750259],"iteration":855,"passed_time":1.055062696,"remaining_time":0.1774871825},
{"learn":[3.254915866],"iteration":856,"passed_time":1.056125038,"remaining_time":0.1762262316},
{"learn":[3.254348625],"iteration":857,"passed_time":1.057616954,"remaining_time":0.1750368386},
{"learn":[3.253408514],"iteration":858,"passed_time":1.058770936,"remaining_time":0.1737912712},
{"learn":[3.253291714],"iteration":859,"passed_time":1.059627745,"remaining_time":0.1724975399},
{"learn":[3.250186342],"iteration":860,"passed_time":1.060604423,"remaining_time":0.1712241751},
{"learn":[3.249141318],"iteration":861,"passed_time":1.061646956,"remaining_time":0.1699620416},
{"learn":[3.246300388],"iteration":862,"passed_time":1.062529431,"remaining_time":0.1686750082},
{"learn":[3.245205135],"iteration":863,"passed_time":1.063618729,"remaining_time":0.1674214666},
{"learn":[3.244403535],"iteration":864,"passed_time":1.064546448,"remaining_time":0.1661430872},
{"learn":[3.244211781],"iteration":865,"passed_time":1.065420113,"remaining_time":0.1648571537},
{"learn":[3.242286347],"iteration":866,"passed_time":1.066316358,"remaining_time":0.1635756351},
{"learn":[3.239606746],"iteration":867,"passed_time":1.067202736,"remaining_time":0.1622935036},
{"learn":[3.236773361],"iteration":868,"passed_time":1.06820668,"remaining_time":0.1610300059},
{"learn":[3.234552446],"iteration":869,"passed_time":1.069140069,"remaining_time":0.159756562},
{"learn":[3.233724647],"iteration":870,"passed_time":1.07035354,"remaining_time":0.1585253807},
{"learn":[3.230851485],"iteration":871,"passed_time":1.071504424,"remaining_time":0.1572850531},
{"learn":[3.227728941],"iteration":872,"passed_time":1.072413802,"remaining_time":0.156009797},
{"learn":[3.225787575],"iteration":873,"passed_time":1.073351211,"remaining_time":0.1547394194},
{"learn":[3.222797487],"iteration":874,"passed_time":1.074607135,"remaining_time":0.153515305},
{"learn":[3.22137014],"iteration":875,"passed_time":1.07555354,"remaining_time":0.1522473048},
{"learn":[3.219701963],"iteration":876,"passed_time":1.076499291,"remaining_time":0.1509799462},
{"learn":[3.21783327],"iteration":877,"passed_time":1.077441884,"remaining_time":0.1497128814},
{"learn":[3.217713355],"iteration":878,"passed_time":1.078381471,"remaining_time":0.1484461411},
{"learn":[3.217666091],"iteration":879,"passed_time":1.079230192,"remaining_time":0.1471677535},
{"learn":[3.214962005],"iteration":880,"passed_time":1.080156769,"remaining_time":0.1459008575},
{"learn":[3.214081828],"iteration":881,"passed_time":1.081042601,"remaining_time":0.1446292823},
{"learn":[3.213358337],"iteration":882,"passed_time":1.081971327,"remaining_time":0.1433642641},
{"learn":[3.210850401],"iteration":883,"passed_time":1.083091667,"remaining_time":0.1421251509},
{"learn":[3.207810328],"iteration":884,"passed_time":1.084430522,"remaining_time":0.1409147006},
{"learn":[3.204935073],"iteration":885,"passed_time":1.085486328,"remaining_time":0.1396675411},
{"learn":[3.20280198],"iteration":886,"passed_time":1.086419529,"remaining_time":0.1384051937},
{"learn":[3.200663495],"iteration":887,"passed_time":1.087669237,"remaining_time":0.1371835074},
{"learn":[3.197301669],"iteration":888,"passed_time":1.088694888,"remaining_time":0.1359337824},
{"learn":[3.195666943],"iteration":889,"passed_time":1.089604281,"remaining_time":0.134670192},
{"learn":[3.193886506],"iteration":890,"passed_time":1.09047717,"remaining_time":0.1334029311},
{"learn":[3.190601248],"iteration":891,"passed_time":1.091379795,"remaining_time":0.1321401546},
{"learn":[3.188983797],"iteration":892,"passed_time":1.092463048,"remaining_time":0.1308998277},
{"learn":[3.187365749],"iteration":893,"passed_time":1.093455102,"remaining_time":0.1296490389},
{"learn":[3.186160771],"iteration":894,"passed_time":1.094338273,"remaining_time":0.1283860544},
{"learn":[3.185358981],"iteration":895,"passed_time":1.095202218,"remaining_time":0.127121686},
{"learn":[3.183832164],"iteration":896,"passed_time":1.096668933,"remaining_time":0.1259274249},
{"learn":[3.183106966],"iteration":897,"passed_time":1.097901214,"remaining_time":0.1247059285},
{"learn":[3.182838152],"iteration":898,"passed_time":1.098828989,"remaining_time":0.1234501979},
{"learn":[3.180835453],"iteration":899,"passed_time":1.099686436,"remaining_time":0.1221873818},
{"learn":[3.179957348],"iteration":900,"passed_time":1.101127215,"remaining_time":0.1209895608},
{"learn":[3.179752966],"iteration":901,"passed_time":1.102174011,"remaining_time":0.1197483958},
{"learn":[3.178851983],"iteration":902,"passed_time":1.103062401,"remaining_time":0.1184906455},
{"learn":[3.176748586],"iteration":903,"passed_time":1.103941238,"remaining_time":0.1172326978},
{"learn":[3.172960988],"iteration":904,"passed_time":1.104752005,"remaining_time":0.1159684425},
{"learn":[3.172794225],"iteration":905,"passed_time":1.105614188,"remaining_time":0.1147105228},
{"learn":[3.169996507],"iteration":906,"passed_time":1.106493355,"remaining_time":0.1134552172},
{"learn":[3.16813015],"iteration":907,"passed_time":1.107423719,"remaining_time":0.1122059275},
{"learn":[3.166920871],"iteration":908,"passed_time":1.108370749,"remaining_time":0.1109590078},
{"learn":[3.16531606],"iteration":909,"passed_time":1.109387056,"remaining_time":0.109719599},
{"learn":[3.162035247],"iteration":910,"passed_time":1.110825848,"remaining_time":0.1085219544},
{"learn":[3.16189467],"iteration":911,"passed_time":1.111878546,"remaining_time":0.1072865263},
{"learn":[3.161008416],"iteration":912,"passed_time":1.112831624,"remaining_time":0.1060420058},
{"learn":[3.160560787],"iteration":913,"passed_time":1.113828399,"remaining_time":0.1048022345},
{"learn":[3.160416261],"iteration":914,"passed_time":1.114876257,"remaining_time":0.1035677397},
{"learn":[3.15844291],"iteration":915,"passed_time":1.115814987,"remaining_time":0.1023236451},
{"learn":[3.155040501],"iteration":916,"passed_time":1.116863367,"remaining_time":0.1010901412},
{"learn":[3.154937548],"iteration":917,"passed_time":1.117747249,"remaining_time":0.09984234686},
{"learn":[3.153721161],"iteration":918,"passed_time":1.118700271,"remaining_time":0.09860143843},
{"learn":[3.153170511],"iteration":919,"passed_time":1.119644728,"remaining_time":0.09736041113},
{"learn":[3.153113601],"iteration":920,"passed_time":1.120517202,"remaining_time":0.09611385334},
{"learn":[3.150607379],"iteration":921,"passed_time":1.121412423,"remaining_time":0.09487003143},
{"learn":[3.148408359],"iteration":922,"passed_time":1.122698574,"remaining_time":0.09365957771},
{"learn":[3.147495728],"iteration":923,"passed_time":1.124323448,"remaining_time":0.09247682043},
{"learn":[3.146946235],"iteration":924,"passed_time":1.125303184,"remaining_time":0.0912407987},
{"learn":[3.14472738],"iteration":925,"passed_time":1.126236915,"remaining_time":0.09000165413},
{"learn":[3.144469477],"iteration":926,"passed_time":1.127182654,"remaining_time":0.08876411407},
{"learn":[3.142975516],"iteration":927,"passed_time":1.128422616,"remaining_time":0.08755003053},
{"learn":[3.14079113],"iteration":928,"passed_time":1.129377051,"remaining_time":0.08631406955},
{"learn":[3.138173032],"iteration":929,"passed_time":1.130358043,"remaining_time":0.08508071294},
{"learn":[3.136352813],"iteration":930,"passed_time":1.131215012,"remaining_time":0.08383870659},
{"learn":[3.133735004],"iteration":931,"passed_time":1.132110735,"remaining_time":0.08260035406},
{"learn":[3.1319496],"iteration":932,"passed_time":1.133018675,"remaining_time":0.08136361331},
{"learn":[3.129865343],"iteration":933,"passed_time":1.133951914,"remaining_time":0.08012936439},
{"learn":[3.129830206],"iteration":934,"passed_time":1.134640005,"remaining_time":0.07887871693},
{"learn":[3.126676562],"iteration":935,"passed_time":1.135499435,"remaining_time":0.07764098698},
{"learn":[3.12645665],"iteration":936,"passed_time":1.137470854,"remaining_time":0.07647883006},
{"learn":[3.126378007],"iteration":937,"passed_time":1.138532282,"remaining_time":0.07525479899},
{"learn":[3.124621914],"iteration":938,"passed_time":1.139432996,"remaining_time":0.07402067386},
{"learn":[3.123379018],"iteration":939,"passed_time":1.140336278,"remaining_time":0.07278742198},
{"learn":[3.123332451],"iteration":940,"passed_time":1.141401628,"remaining_time":0.07156503299},
{"learn":[3.122432444],"iteration":941,"passed_time":1.142346095,"remaining_time":0.07033553453},
{"learn":[3.121889006],"iteration":942,"passed_time":1.143412116,"remaining_time":0.0691139879},
{"learn":[3.121070914],"iteration":943,"passed_time":1.144278528,"remaining_time":0.06788092965},
{"learn":[3.118444705],"iteration":944,"passed_time":1.145141142,"remaining_time":0.06664842626},
{"learn":[3.116820458],"iteration":945,"passed_time":1.146001995,"remaining_time":0.06541660438},
{"learn":[3.114971041],"iteration":946,"passed_time":1.146964512,"remaining_time":0.06419125571},
{"learn":[3.114685138],"iteration":947,"passed_time":1.147788635,"remaining_time":0.06295887029},
{"learn":[3.113399363],"iteration":948,"passed_time":1.148834029,"remaining_time":0.06173923656},
{"learn":[3.110575399],"iteration":949,"passed_time":1.150282017,"remaining_time":0.06054115877},
{"learn":[3.110466553],"iteration":950,"passed_time":1.151234371,"remaining_time":0.05931701804},
{"learn":[3.108691641],"iteration":951,"passed_time":1.152169709,"remaining_time":0.05809259035},
{"learn":[3.107898017],"iteration":952,"passed_time":1.153064832,"remaining_time":0.05686678604},
{"learn":[3.105551729],"iteration":953,"passed_time":1.154267631,"remaining_time":0.05565651052},
{"learn":[3.104824945],"iteration":954,"passed_time":1.155281991,"remaining_time":0.05443737132},
{"learn":[3.103186704],"iteration":955,"passed_time":1.156244308,"remaining_time":0.05321626521},
{"learn":[3.102330655],"iteration":956,"passed_time":1.157141951,"remaining_time":0.05199279403},
{"learn":[3.102291298],"iteration":957,"passed_time":1.158042625,"remaining_time":0.05077013598},
{"learn":[3.100363529],"iteration":958,"passed_time":1.158950077,"remaining_time":0.04954843916},
{"learn":[3.097871596],"iteration":959,"passed_time":1.159975687,"remaining_time":0.04833232029},
{"learn":[3.097372213],"iteration":960,"passed_time":1.160879892,"remaining_time":0.04711167094},
{"learn":[3.095981813],"iteration":961,"passed_time":1.161802784,"remaining_time":0.04589241766},
{"learn":[3.095347452],"iteration":962,"passed_time":1.162744674,"remaining_time":0.04467450982},
{"learn":[3.094728409],"iteration":963,"passed_time":1.164375248,"remaining_time":0.04348289306},
{"learn":[3.094118537],"iteration":964,"passed_time":1.165377737,"remaining_time":0.04226758631},
{"learn":[3.093793695],"iteration":965,"passed_time":1.166244471,"remaining_time":0.04104794205},
{"learn":[3.092581602],"iteration":966,"passed_time":1.167728973,"remaining_time":0.03985010973},
{"learn":[3.091694202],"iteration":967,"passed_time":1.168709847,"remaining_time":0.03863503627},
{"learn":[3.090298312],"iteration":968,"passed_time":1.169661908,"remaining_time":0.0374195244},
{"learn":[3.090020107],"iteration":969,"passed_time":1.17052586,"remaining_time":0.03620183073},
{"learn":[3.088949869],"iteration":970,"passed_time":1.171440634,"remaining_time":0.03498638352},
{"learn":[3.086700204],"iteration":971,"passed_time":1.172521932,"remaining_time":0.03377635196},
{"learn":[3.086584317],"iteration":972,"passed_time":1.173378938,"remaining_time":0.03256036107},
{"learn":[3.084850742],"iteration":973,"passed_time":1.174420737,"remaining_time":0.03135004022},
{"learn":[3.084239948],"iteration":974,"passed_time":1.175392634,"remaining_time":0.03013827268},
{"learn":[3.082561673],"iteration":975,"passed_time":1.176346089,"remaining_time":0.02892654317},
{"learn":[3.07991814],"iteration":976,"passed_time":1.178618779,"remaining_time":0.0277463991},
{"learn":[3.079350277],"iteration":977,"passed_time":1.179474473,"remaining_time":0.02653214561},
{"learn":[3.077637462],"iteration":978,"passed_time":1.180385738,"remaining_time":0.02531981665},
{"learn":[3.076733301],"iteration":979,"passed_time":1.181469058,"remaining_time":0.02411161342},
{"learn":[3.07594065],"iteration":980,"passed_time":1.182359738,"remaining_time":0.02289993377},
{"learn":[3.072594655],"iteration":981,"passed_time":1.183250918,"remaining_time":0.02168891703},
{"learn":[3.071977674],"iteration":982,"passed_time":1.184186965,"remaining_time":0.02047932696},
{"learn":[3.069532634],"iteration":983,"passed_time":1.185163434,"remaining_time":0.01927095015},
{"learn":[3.068870784],"iteration":984,"passed_time":1.186028812,"remaining_time":0.01806135247},
{"learn":[3.068801463],"iteration":985,"passed_time":1.186848773,"remaining_time":0.01685180814},
{"learn":[3.067433249],"iteration":986,"passed_time":1.18773449,"remaining_time":0.01564391932},
{"learn":[3.065611456],"iteration":987,"passed_time":1.188689533,"remaining_time":0.01443752469},
{"learn":[3.063039162],"iteration":988,"passed_time":1.189672265,"remaining_time":0.01323194632},
{"learn":[3.06177873],"iteration":989,"passed_time":1.190771811,"remaining_time":0.01202799809},
{"learn":[3.061689148],"iteration":990,"passed_time":1.191854712,"remaining_time":0.01082410939},
{"learn":[3.058984039],"iteration":991,"passed_time":1.192791353,"remaining_time":0.009619285107},
{"learn":[3.057492984],"iteration":992,"passed_time":1.193940137,"remaining_time":0.008416496431},
{"learn":[3.057290731],"iteration":993,"passed_time":1.194953256,"remaining_time":0.007212997518},
{"learn":[3.056068348],"iteration":994,"passed_time":1.195844942,"remaining_time":0.006009271066},
{"learn":[3.054987307],"iteration":995,"passed_time":1.196743203,"remaining_time":0.004806197602},
{"learn":[3.054200234],"iteration":996,"passed_time":1.197673339,"remaining_time":0.00360383151},
{"learn":[3.052732869],"iteration":997,"passed_time":1.198621242,"remaining_time":0.002402046578},
{"learn":[3.051787862],"iteration":998,"passed_time":1.199548913,"remaining_time":0.001200749663},
{"learn":[3.051366222],"iteration":999,"passed_time":1.200381927,"remaining_time":0}
]}